{"0": [], "1": [{"name": "\u5efa\u7bc9\u5c08\u696d\u5b78\u9662", "unit": [{"name": "\u5efa\u7bc9\u5c08\u696d\u5b78\u9662", "id": "AS00"}, {"name": "\u5efa\u7bc9\u5c08\u696d\u5b78\u9662\u5b78\u58eb\u73ed", "id": "AS01"}, {"name": "\u5efa\u7bc9\u5b78\u58eb\u5b78\u4f4d\u5b78\u7a0b", "id": "CE03"}], "id": "AS"}, {"name": "\u5546\u5b78\u9662", "unit": [{"name": "\u5546\u5b78\u9662", "id": "CB00"}, {"name": "\u6703\u8a08\u7cfb", "id": "CB01"}, {"name": "\u4f01\u7ba1\u7cfb", "id": "CM01"}, {"name": "\u570b\u969b\u7d93\u71df\u8207\u8cbf\u6613\u5b78\u7cfb", "id": "CB02"}, {"name": "\u8ca1\u7a05\u7cfb", "id": "CB05"}, {"name": "\u7d71\u8a08\u7cfb", "id": "CB07"}, {"name": "\u7d93\u6fdf\u7cfb", "id": "CB08"}, {"name": "\u5408\u4f5c\u7d93\u6fdf\u66a8\u793e\u6703\u4e8b\u696d\u7d93\u71df\u5b78\u7cfb", "id": "CB06"}, {"name": "\u884c\u92b7\u7cfb", "id": "CB26"}, {"name": "\u570b\u4f01\u5b78\u58eb\u5b78\u7a0b\u82f1\u8a9e\u5c08\u73ed", "id": "CB25"}], "id": "CB"}, {"name": "\u5efa\u8a2d\u5b78\u9662", "unit": [{"name": "\u5efa\u8a2d\u5b78\u9662", "id": "CD00"}, {"name": "\u571f\u6728\u7cfb", "id": "CE01"}, {"name": "\u6c34\u5229\u7cfb", "id": "CE02"}, {"name": "\u904b\u7ba1\u7cfb", "id": "CM02"}, {"name": "\u90fd\u8cc7\u7cfb", "id": "CE10"}, {"name": "\u571f\u7ba1\u7cfb", "id": "CM03"}], "id": "CD"}, {"name": "\u5de5\u5b78\u9662", "unit": [{"name": "\u5de5\u5b78\u9662", "id": "CE00"}, {"name": "\u7e96\u7dad\u8907\u6750\u7cfb", "id": "CE05"}, {"name": "\u6a5f\u96fb\u7cfb", "id": "CE04"}, {"name": "\u5de5\u5de5\u7cfb", "id": "CE06"}, {"name": "\u5316\u5de5\u7cfb", "id": "CE08"}, {"name": "\u822a\u592a\u7cfb", "id": "CE13"}, {"name": "\u7cbe\u5bc6\u7cfb\u7d71\u8a2d\u8a08\u5b78\u4f4d\u5b78\u7a0b", "id": "CE26"}], "id": "CE"}, {"name": "\u91d1\u878d\u5b78\u9662", "unit": [{"name": "\u91d1\u878d\u5b78\u9662", "id": "CF00"}, {"name": "\u8ca1\u91d1\u7cfb", "id": "CB03"}, {"name": "\u98a8\u4fdd\u7cfb", "id": "CB04"}, {"name": "\u8ca1\u52d9\u5de5\u7a0b\u8207\u7cbe\u7b97\u5b78\u7a0b", "id": "CF03"}], "id": "CF"}, {"name": "\u4eba\u793e\u5b78\u9662", "unit": [{"name": "\u4eba\u793e\u5b78\u9662", "id": "CH00"}, {"name": "\u4e2d\u6587\u7cfb", "id": "CS04"}, {"name": "\u5916\u6587\u7cfb", "id": "CH06"}], "id": "CH"}, {"name": "\u8cc7\u96fb\u5b78\u9662", "unit": [{"name": "\u8cc7\u96fb\u5b78\u9662", "id": "CI00"}, {"name": "\u8cc7\u8a0a\u7cfb", "id": "CE07"}, {"name": "\u96fb\u5b50\u7cfb", "id": "CE09"}, {"name": "\u96fb\u6a5f\u7cfb", "id": "CE11"}, {"name": "\u81ea\u63a7\u7cfb", "id": "CE12"}, {"name": "\u901a\u8a0a\u7cfb", "id": "CI02"}, {"name": "\u8cc7\u96fb\u69ae\u8b7d\u73ed", "id": "CI05"}], "id": "CI"}, {"name": "\u7406\u5b78\u9662", "unit": [{"name": "\u7406\u5b78\u9662", "id": "CS00"}, {"name": "\u61c9\u6578\u7cfb", "id": "CS01"}, {"name": "\u74b0\u79d1\u7cfb", "id": "CS02"}, {"name": "\u6750\u6599\u7cfb", "id": "CS03"}, {"name": "\u5149\u96fb\u5b78\u7cfb", "id": "CS06"}], "id": "CS"}, {"name": "\u570b\u969b\u79d1\u6280\u8207\u7ba1\u7406\u5b78\u9662", "unit": [{"name": "\u570b\u969b\u79d1\u6280\u8207\u7ba1\u7406\u5b78\u9662", "id": "NM00"}, {"name": "\u6fb3\u6d32\u58a8\u723e\u672c\u7687\u5bb6\u7406\u5de5\u5927\u5b78\u5546\u5b78", "id": "NM02"}, {"name": "\u96fb\u6a5f\u8cc7\u8a0a\u96d9\u5b78\u58eb\u5b78\u4f4d\u5b78\u7a0b", "id": "NM03"}, {"name": "\u5546\u5b78\u5927\u6578\u64da\u5206\u6790\u96d9\u5b78\u58eb\u5b78\u4f4d\u5b78", "id": "NM04"}], "id": "NM"}, {"name": "\u5b78\u5206\u5b78\u7a0b", "unit": [{"name": "\u6cd5\u5f8b\u7d93\u6fdf\u5b78\u7a0b", "id": "PC04"}, {"name": "\u4e0d\u52d5\u7522\u7ba1\u7406\u5b78\u7a0b", "id": "PC14"}, {"name": "\u666f\u89c0\u8207\u904a\u61a9\u7ba1\u7406\u5b78\u7a0b", "id": "PC15"}, {"name": "\u6c11\u822a\u98db\u884c\u5b78\u7a0b", "id": "PC21"}, {"name": "\u793e\u6703\u50b3\u64ad\u5b78\u7a0b", "id": "PC22"}, {"name": "\u83c1\u82f1\u82f1\u8a9e\u5b78\u7a0b", "id": "PC23"}, {"name": "\u5275\u65b0\u5275\u696d\u5b78\u7a0b", "id": "PC27"}, {"name": "\u6c34\u571f\u74b0\u5883\u7d93\u7406\u5b78\u7a0b", "id": "PC28"}, {"name": "\u83ef\u8a9e\u6559\u5e2b\u5b78\u7a0b", "id": "PC29"}, {"name": "\u8a08\u7b97\u79d1\u5b78\u5b78\u7a0b", "id": "PC30"}, {"name": "\u61c9\u7528\u5916\u8a9e\u5b78\u7a0b", "id": "PC35"}, {"name": "\u52de\u5de5\u5b89\u5168\u885b\u751f\u5b78\u7a0b", "id": "PC44"}, {"name": "\u5c08\u6848\u7ba1\u7406\u5b78\u7a0b", "id": "PC46"}, {"name": "\u61c9\u7528\u65e5\u8a9e\u5b78\u7a0b", "id": "PC47"}, {"name": "\u7da0\u8272\u80fd\u6e90\u79d1\u6280\u5b78\u7a0b", "id": "PC50"}, {"name": "\u76ae\u9769\u79d1\u6280\u8207\u7ba1\u7406\u5b78\u7a0b", "id": "PC56"}, {"name": "\u9f0e\u65b0\u96fb\u8166\u5c31\u696d\u5b78\u7fd2\u5b78\u7a0b", "id": "PC59"}, {"name": "\u6d41\u9ad4\u50b3\u52d5\u79d1\u6280\u5b78\u7a0b", "id": "PC63"}, {"name": "\u6210\u8863\u83c1\u82f1\u5b78\u7a0b", "id": "PC64"}, {"name": "\u978b\u985e\u7522\u696d\u4eba\u624d\u5b78\u7a0b", "id": "PC67"}], "id": "PC"}, {"name": "\u901a\u8b58\u6838\u5fc3\u8ab2", "unit": [{"name": "\u901a\u8b58\u6838\u5fc3", "id": "XC01"}], "id": "XC"}, {"name": "\u9ad4\u80b2\u9078\u9805\u8ab2", "unit": [{"name": "\u9ad4\u80b2\u9078\u9805\u8ab2", "id": "XD01"}], "id": "XD"}, {"name": "\u7d9c\u5408\u73ed", "unit": [{"name": "\u7d9c\u5408\u73ed", "id": "XE01"}], "id": "XE"}, {"name": "\u7d71\u7c4c\u79d1\u76ee", "unit": [{"name": "\u82f1\u6587\u7d9c\u5408\u73ed", "id": "XF01"}, {"name": "\u570b\u6587\u7d9c\u5408\u73ed", "id": "XF02"}, {"name": "\u7d93\u6fdf\u5b78\u7d9c\u5408\u73ed", "id": "XF03"}, {"name": "\u7ba1\u7406\u5b78\u7d9c\u5408\u73ed", "id": "XF06"}, {"name": "\u6838\u5fc3\u5fc5\u4fee\u7d9c\u5408\u73ed", "id": "XF07"}], "id": "XF"}, {"name": "\u8ecd\u8a13", "unit": [{"name": "\u8ecd\u8a13", "id": "XH01"}], "id": "XH"}], "2": [{"name": "\u901a\u8b58\u6838\u5fc3\u8ab2", "unit": [{"name": "\u901a\u8b58\u6838\u5fc3", "id": "XC01"}], "id": "XC"}], "3": [{"name": "\u5efa\u7bc9\u5c08\u696d\u5b78\u9662", "unit": [{"name": "\u5efa\u7bc9\u78a9\u58eb\u5b78\u4f4d\u5b78\u7a0b", "id": "AS04"}, {"name": "\u5efa\u7bc9\u78a9\u58eb\u5728\u8077\u5b78\u4f4d\u5b78\u7a0b", "id": "AS05"}], "id": "AS"}, {"name": "\u5546\u5b78\u9662", "unit": [{"name": "\u6703\u8a08\u7cfb", "id": "CB01"}, {"name": "\u4f01\u7ba1\u7cfb", "id": "CM01"}, {"name": "\u570b\u969b\u7d93\u71df\u8207\u8cbf\u6613\u5b78\u7cfb", "id": "CB02"}, {"name": "\u8ca1\u7a05\u7cfb", "id": "CB05"}, {"name": "\u7d71\u8a08\u7cfb", "id": "CB07"}, {"name": "\u7d93\u6fdf\u7cfb", "id": "CB08"}, {"name": "\u5408\u4f5c\u7d93\u6fdf\u66a8\u793e\u6703\u4e8b\u696d\u7d93\u71df\u5b78\u7cfb", "id": "CB06"}, {"name": "\u8ca1\u6cd5\u6240", "id": "CB15"}, {"name": "\u79d1\u6280\u7ba1\u7406\u78a9\u58eb\u5b78\u4f4d\u5b78\u7a0b", "id": "CB21"}, {"name": "\u7522\u696d\u78a9\u58eb\u5c08\u73ed", "id": "CB29"}, {"name": "\u5546\u5b78\u9662\u5546\u5b78\u5c08\u696d\u78a9\u58eb\u5728\u8077\u5c08\u73ed", "id": "CB31"}], "id": "CB"}, {"name": "\u5efa\u8a2d\u5b78\u9662", "unit": [{"name": "\u5efa\u8a2d\u5b78\u9662", "id": "CD00"}, {"name": "\u571f\u6728\u7cfb", "id": "CE01"}, {"name": "\u6c34\u5229\u7cfb", "id": "CE02"}, {"name": "\u904b\u7ba1\u7cfb", "id": "CM02"}, {"name": "\u90fd\u8cc7\u7cfb", "id": "CE10"}, {"name": "\u571f\u7ba1\u7cfb", "id": "CM03"}, {"name": "\u666f\u61a9\u78a9\u58eb\u5b78\u4f4d\u5b78\u7a0b", "id": "CD03"}, {"name": "\u5efa\u8a2d\u5b78\u9662\u5c08\u6848\u7ba1\u7406\u78a9\u58eb\u5728\u8077\u5c08", "id": "CD13"}], "id": "CD"}, {"name": "\u5de5\u5b78\u9662", "unit": [{"name": "\u7e96\u7dad\u8907\u6750\u7cfb", "id": "CE05"}, {"name": "\u6a5f\u96fb\u7cfb", "id": "CE04"}, {"name": "\u5de5\u5de5\u7cfb", "id": "CE06"}, {"name": "\u5316\u5de5\u7cfb", "id": "CE08"}, {"name": "\u822a\u592a\u7cfb", "id": "CE13"}, {"name": "\u96fb\u8072\u78a9\u58eb\u5b78\u4f4d\u5b78\u7a0b", "id": "CE19"}, {"name": "\u7da0\u80fd\u78a9\u58eb\u5b78\u4f4d\u5b78\u7a0b", "id": "CE24"}, {"name": "\u5275\u610f\u8a2d\u8a08\u78a9\u58eb\u5b78\u4f4d\u5b78\u7a0b", "id": "CE25"}, {"name": "\u7522\u696d\u78a9\u58eb\u5c08\u73ed", "id": "CE29"}], "id": "CE"}, {"name": "\u91d1\u878d\u5b78\u9662", "unit": [{"name": "\u8ca1\u91d1\u7cfb", "id": "CB03"}, {"name": "\u98a8\u4fdd\u7cfb", "id": "CB04"}, {"name": "\u91d1\u878d\u78a9\u58eb\u5728\u8077\u5c08\u73ed", "id": "CF02"}], "id": "CF"}, {"name": "\u4eba\u793e\u5b78\u9662", "unit": [{"name": "\u4e2d\u6587\u7cfb", "id": "CS04"}, {"name": "\u5916\u6587\u7cfb", "id": "CH06"}, {"name": "\u6b77\u53f2\u6587\u7269\u6240", "id": "CH07"}, {"name": "\u516c\u5171\u653f\u7b56\u6240", "id": "CH08"}], "id": "CH"}, {"name": "\u8cc7\u96fb\u5b78\u9662", "unit": [{"name": "\u8cc7\u8a0a\u7cfb", "id": "CE07"}, {"name": "\u96fb\u5b50\u7cfb", "id": "CE09"}, {"name": "\u96fb\u6a5f\u7cfb", "id": "CE11"}, {"name": "\u81ea\u63a7\u7cfb", "id": "CE12"}, {"name": "\u901a\u8a0a\u7cfb", "id": "CI02"}, {"name": "\u8cc7\u96fb\u78a9\u58eb\u5728\u8077\u73ed", "id": "CI06"}, {"name": "\u7522\u696d\u7814\u767c\u78a9\u58eb\u73ed", "id": "CI10"}, {"name": "\u751f\u91ab\u78a9\u58eb\u5b78\u4f4d\u5b78\u7a0b", "id": "CI13"}, {"name": "\u5149\u96fb\u80fd\u6e90\u78a9\u58eb\u5728\u8077\u5c08\u73ed", "id": "CI17"}], "id": "CI"}, {"name": "\u7406\u5b78\u9662", "unit": [{"name": "\u61c9\u6578\u7cfb", "id": "CS01"}, {"name": "\u74b0\u79d1\u7cfb", "id": "CS02"}, {"name": "\u6750\u6599\u7cfb", "id": "CS03"}, {"name": "\u5149\u96fb\u5b78\u7cfb", "id": "CS06"}], "id": "CS"}, {"name": "\u7d93\u7ba1\u5b78\u9662", "unit": [{"name": "\u7d93\u71df\u5728\u8077\u5c08\u73ed", "id": "CB13"}, {"name": "\u96fb\u5b50\u5546\u52d9\u5c08\u73ed", "id": "MB02"}], "id": "MB"}, {"name": "\u570b\u969b\u79d1\u6280\u8207\u7ba1\u7406\u5b78\u9662", "unit": [{"name": "\u570b\u969b\u7d93\u7ba1\u78a9\u58eb\u5b78\u4f4d\u5b78\u7a0b", "id": "CB23"}, {"name": "\u7269\u6d41\u4f9b\u61c9\u93c8\u7ba1\u7406\u8207\u5275\u65b0\u5275\u696d\u96d9", "id": "NM01"}], "id": "NM"}, {"name": "\u5b78\u5206\u5b78\u7a0b", "unit": [{"name": "\u667a\u8ca1\u6280\u8f49\u5b78\u7a0b(\u78a9\u58eb\u73ed)", "id": "PC76"}], "id": "PC"}], "4": [{"name": "\u5546\u5b78\u9662", "unit": [{"name": "\u7d71\u8a08\u7cfb", "id": "CB07"}, {"name": "\u7d93\u6fdf\u7cfb", "id": "CB08"}, {"name": "\u5546\u5b78\u535a\u58eb\u5b78\u4f4d\u5b78\u7a0b", "id": "CB16"}], "id": "CB"}, {"name": "\u5efa\u8a2d\u5b78\u9662", "unit": [{"name": "\u571f\u6c34\u535a\u58eb\u5b78\u4f4d\u5b78\u7a0b", "id": "CE14"}], "id": "CD"}, {"name": "\u5de5\u5b78\u9662", "unit": [{"name": "\u7e96\u7dad\u8907\u6750\u7cfb", "id": "CE05"}, {"name": "\u5de5\u5de5\u7cfb", "id": "CE06"}, {"name": "\u5316\u5de5\u7cfb", "id": "CE08"}, {"name": "\u6a5f\u822a\u535a\u58eb\u5b78\u4f4d\u5b78\u7a0b", "id": "CE17"}], "id": "CE"}, {"name": "\u91d1\u878d\u5b78\u9662", "unit": [{"name": "\u91d1\u878d\u535a\u58eb\u5b78\u4f4d\u5b78\u7a0b", "id": "CF01"}], "id": "CF"}, {"name": "\u4eba\u793e\u5b78\u9662", "unit": [{"name": "\u4e2d\u6587\u7cfb", "id": "CS04"}], "id": "CH"}, {"name": "\u8cc7\u96fb\u5b78\u9662", "unit": [{"name": "\u8cc7\u8a0a\u7cfb", "id": "CE07"}, {"name": "\u96fb\u901a\u535a\u58eb\u5b78\u4f4d\u5b78\u7a0b", "id": "CI03"}, {"name": "\u667a\u6167\u806f\u7db2\u7522\u696d\u535a\u58eb\u5b78\u4f4d\u5b78\u7a0b", "id": "CI21"}], "id": "CI"}, {"name": "\u7406\u5b78\u9662", "unit": [{"name": "\u74b0\u79d1\u7cfb", "id": "CS02"}, {"name": "\u6750\u6599\u7cfb", "id": "CS03"}], "id": "CS"}], "5": [{"name": "\u5efa\u7bc9\u5c08\u696d\u5b78\u9662", "unit": [{"name": "\u5ba4\u5167\u8a2d\u8a08\u9032\u4fee\u5b78\u58eb\u73ed", "id": "CD01"}], "id": "AS"}, {"name": "\u5546\u5b78\u9662", "unit": [{"name": "\u5546\u5b78\u9032\u4fee\u73ed", "id": "CB14"}], "id": "CB"}, {"name": "\u5efa\u8a2d\u5b78\u9662", "unit": [{"name": "\u71df\u5efa\u5de5\u7a0b\u8207\u7ba1\u7406\u9032\u4fee\u5b78\u58eb\u73ed", "id": "CD06"}], "id": "CD"}, {"name": "\u7d71\u7c4c\u79d1\u76ee", "unit": [{"name": "\u82f1\u6587\u7d9c\u5408\u73ed", "id": "XF01"}], "id": "XF"}]}