{"1052CB0111351950001": {"scr_period": "(\u4e09)01-02 \u79d1\u822a205 \u5ed6\u5049\u5609", "scr_acptcnt": 58.0, "sub_name": "ACCT111P \u6703\u8a08\u5b78(\u4e00)\u5be6\u7fd2", "scj_scr_mso": "\u5fc5\u4fee", "scr_precnt": 85.0, "year": 105, "semester": 1, "scr_selcode": "0039", "scr_credit": 0.0, "unt_ls": 4101, "scr_dup": "001", "scr_remarks": "\u9808\u96a8\u73ed\u4fee\u7fd2\u9078\u8ab2\u4ee3\u865f0038\u300c\u6703\u8a08\u5b78(\u4e00)\u300d\u6b63\u8ab2", "cls_name": "\u6703\u8a08\u4e00\u4e19", "sub_id": "51950", "scr_exambf": "\u5426", "cls_id": "CB01113", "scr_examid": "\u5426", "scr_examfn": "\u5426"}, "1052CE0313143034001": {"scr_period": "(\u4e09)01-02 \u8a9e202 \u6590\u514b\u79ae", "scr_acptcnt": 54.0, "sub_name": "GBEN101 \u5c08\u696d\u5916\u8a9e", "scj_scr_mso": "\u5fc5\u4fee", "scr_precnt": 60.0, "year": 105, "semester": 1, "scr_selcode": "1260", "scr_credit": 2.0, "unt_ls": 5002, "scr_dup": "001", "scr_remarks": " ", "cls_name": "\u5efa\u7bc9\u4e09\u7532\u5b78\u4f4d\u5b78\u7a0b", "sub_id": "43034", "scr_exambf": "\u5426", "cls_id": "CE03131", "scr_examid": "\u5426", "scr_examfn": "\u5426"}, "1052CE1232011810001": {"scr_period": "(\u4e8c)07     \u8cc7\u96fb418 \u90b1\u5275\u4e7e,\u6797\u8ce2\u9f8d", "scr_acptcnt": 25.0, "sub_name": "AUTO691 \u6587\u737b\u7814\u8a0e(\u4e00)", "scj_scr_mso": "\u5fc5\u4fee", "scr_precnt": 40.0, "year": 105, "semester": 1, "scr_selcode": "1982", "scr_credit": 1.0, "unt_ls": 4504, "scr_dup": "001", "scr_remarks": " ", "cls_name": "\u81ea\u63a7\u78a9\u4e8c", "sub_id": "11810", "scr_exambf": "\u5426", "cls_id": "CE12320", "scr_examid": "\u5426", "scr_examfn": "\u5426"}, "1052CE0711160520001": {"scr_period": "(\u4e09)03-04 \u5fe0B01 (\u4e94)04     \u5fe0B05 \u66fe\u52f5\u65b0", "scr_acptcnt": 81.0, "sub_name": "MATH105 \u5fae\u7a4d\u5206(\u4e00)", "scj_scr_mso": "\u5fc5\u4fee", "scr_precnt": 8.0, "year": 105, "semester": 1, "scr_selcode": "1624", "scr_credit": 3.0, "unt_ls": 4501, "scr_dup": "001", "scr_remarks": " ", "cls_name": "\u8cc7\u8a0a\u4e00\u7532", "sub_id": "60520", "scr_exambf": "\u5426", "cls_id": "CE07111", "scr_examid": "\u662f", "scr_examfn": "\u662f"}, "1052XC01128GNE03001": {"scr_period": "(\u4e8c)09-10 \u4eba501 \u674e\u627f\u5b97", "scr_acptcnt": 53.0, "sub_name": "GNAEE03 \u97f3\u6a02\u3001\u8a9e\u8a00\u8207\u5927\u8166", "scj_scr_mso": "\u9078\u4fee", "scr_precnt": 60.0, "year": 105, "semester": 1, "scr_selcode": "3558", "scr_credit": 2.0, "unt_ls": 8888, "scr_dup": "001", "scr_remarks": "\u662f\u5426\u5217\u5165\u7562\u696d\u5b78\u5206\u8acb\u81f3\u5404\u7cfb\u78ba\u8a8d\u3002\u8a73\u60c5  \u8acb\u53c3\u95b1\u300c\u901a\u8b58\u8ab2\u7a0b\u9078\u8ab2\u9808\u77e5\u300d\u3002", "cls_name": "\u901a\u8b58\uff0d\u81ea\u7136\u5168\u82f1\u8a9e(NE)", "sub_id": "GNE03", "scr_exambf": "\u5426", "cls_id": "XC01128", "scr_examid": "\u5426", "scr_examfn": "\u662f"}, "1052CB0214130636001": {"scr_period": "(\u4e94)06     \u555f\u57a3\u5ef3 \u6c5f\u6021\u84a8", "scr_acptcnt": 315.0, "sub_name": "UNIV909 \u6821\u5916\u5be6\u7fd2\u5c0e\u8ad6", "scj_scr_mso": "\u9078\u4fee", "scr_precnt": 380.0, "year": 105, "semester": 1, "scr_selcode": "0213", "scr_credit": 1.0, "unt_ls": 4103, "scr_dup": "001", "scr_remarks": "\u9650\u5546\u5b78\u9662\u5b78\u751f\u4fee\u8ab2", "cls_name": "\u570b\u8cbf\u56db\u7532", "sub_id": "30636", "scr_exambf": "\u5426", "cls_id": "CB02141", "scr_examid": "\u5426", "scr_examfn": "\u5426"}, "1052PC5010011945001": {"scr_period": "(\u56db)02-04 \u8a9e402 \u6797\u5b6b\u57fa", "scr_acptcnt": 66.0, "sub_name": "GEST422 \u751f\u8cea\u80fd\u6e90", "scj_scr_mso": "\u9078\u4fee", "scr_precnt": 70.0, "year": 105, "semester": 1, "scr_selcode": "3447", "scr_credit": 3.0, "unt_ls": 8888, "scr_dup": "001", "scr_remarks": null, "cls_name": "\u7da0\u8272\u80fd\u6e90\u79d1\u6280\u5b78\u7a0b", "sub_id": "11945", "scr_exambf": "\u5426", "cls_id": "PC50100", "scr_examid": "\u662f", "scr_examfn": "\u5426"}, "1052CI0084L23014001": {"scr_period": "(\u4e8c)06-07 \u8cc7\u96fb512 (\u56db)06     \u8cc7\u96fb512 \u9ec3\u5efa\u7acb", "scr_acptcnt": 20.0, "sub_name": "AUTO426 \u79d1\u6280\u7522\u696d\u5de5\u7a0b", "scj_scr_mso": "\u9078\u4fee", "scr_precnt": 60.0, "year": 105, "semester": 1, "scr_selcode": "2497", "scr_credit": 3.0, "unt_ls": 4504, "scr_dup": "001", "scr_remarks": " ", "cls_name": "\u5149\u6a5f\u96fb\u5de5\u7a0b\u5b78\u7a0b\u81ea\u63a7\u56db", "sub_id": "23014", "scr_exambf": "\u5426", "cls_id": "CI0084L", "scr_examid": "\u662f", "scr_examfn": "\u5426"}, "1052CE0541043130001": {"scr_period": "(\u4e00)02     \u5de5310 \u6797\u4f73\u5f18", "scr_acptcnt": 4.0, "sub_name": "COE701 \u5c08\u984c\u8a0e\u8ad6(\u4e00)", "scj_scr_mso": "\u5fc5\u4fee", "scr_precnt": 15.0, "year": 105, "semester": 1, "scr_selcode": "1527", "scr_credit": 1.0, "unt_ls": 4008, "scr_dup": "001", "scr_remarks": " ", "cls_name": "\u7e96\u8907\u535a\u4e00", "sub_id": "43130", "scr_exambf": "\u5426", "cls_id": "CE05410", "scr_examid": "\u5426", "scr_examfn": "\u5426"}, "1052XH0111113891002": {"scr_period": "(\u4e09)03-04 \u7537\u820dB03 \u7fc1\u9ad8\u6587,\u6d2a\u975c\u8339", "scr_acptcnt": 102.0, "sub_name": "MILT121 \u5168\u6c11\u570b\u9632\u6559\u80b2\u8ecd\u4e8b\u8a13\u7df4(\u4e00)", "scj_scr_mso": "\u5fc5\u4fee", "scr_precnt": 120.0, "year": 105, "semester": 1, "scr_selcode": "4374", "scr_credit": 0.0, "unt_ls": 8888, "scr_dup": "002", "scr_remarks": "\u672c\u8ab2\u7a0b\u9700\u5be6\u65bd\u8cc7\u8a0a\u7d20\u990a--\u5371\u6a5f\u8655\u7406\u8ab2\u7a0b   \uff0c\u8acb\u91cd\u88dc\u4fee\u751f\u638c\u63e1\u76f8\u95dc\u9078\u8ab2\u8a0a\u606f", "cls_name": "\u8ecd\u8a13(\u4e00\u5e74\u7d1a)", "sub_id": "13891", "scr_exambf": "\u5426", "cls_id": "XH01111", "scr_examid": "\u5426", "scr_examfn": "\u5426"}, "1052CM0132044453001": {"scr_period": "(\u65e5)05     \u672a\u6392\u6559\u5ba4 \u9ec3\u8aa0\u752b,\u5f35\u79c0\u6a3a", "scr_acptcnt": 3.0, "sub_name": "MGT711 \u6691\u671f\u6821\u5916\u5c08\u696d\u5be6\u7fd2(\u4e00)", "scj_scr_mso": "\u9078\u4fee", "scr_precnt": 20.0, "year": 105, "semester": 1, "scr_selcode": "4429", "scr_credit": 1.0, "unt_ls": 4102, "scr_dup": "001", "scr_remarks": null, "cls_name": "\u4f01\u7ba1\u78a9\u4e8c", "sub_id": "44453", "scr_exambf": "\u5426", "cls_id": "CM01320", "scr_examid": "\u5426", "scr_examfn": "\u5426"}, "1052CE0313224050001": {"scr_period": "(\u4e00)01-03 \u5fe0515(\u5efa\u88fd\u5716\u5ba4) (\u4e00)03     \u5fe0516(\u5efa\u88fd\u5716\u5ba4) (\u4e00)03     \u5fe0804 (\u4e00)04     \u5fe0515(\u5efa\u88fd\u5716\u5ba4) (\u4e00)04     \u5fe0516(\u5efa\u88fd\u5716\u5ba4) (\u4e00)04     \u5fe0804 (\u4e00)06     \u5fe0515(\u5efa\u88fd\u5716\u5ba4) (\u4e00)06     \u5fe0516(\u5efa\u88fd\u5716\u5ba4) (\u4e00)06     \u5fe0804 (\u4e00)07     \u5fe0515(\u5efa\u88fd\u5716\u5ba4) (\u4e00)07", "scr_acptcnt": 123.0, "sub_name": "ARCH301 \u5efa\u7bc9\u8a2d\u8a08(\u4e94)", "scj_scr_mso": "\u5fc5\u4fee", "scr_precnt": 120.0, "year": 105, "semester": 1, "scr_selcode": "1268", "scr_credit": 3.0, "unt_ls": 5002, "scr_dup": "001", "scr_remarks": null, "cls_name": "\u5efa\u7bc9\u4e09\u4e59\u5b78\u4f4d\u5b78\u7a0b", "sub_id": "24050", "scr_exambf": "\u5426", "cls_id": "CE03132", "scr_examid": "\u5426", "scr_examfn": "\u5426"}, "1052CE1312202270001": {"scr_period": "(\u4e8c)09     \u79d1\u822a206 (\u4e09)01-02 \u79d1\u822a206 \u674e\u6c38\u660e", "scr_acptcnt": 63.0, "sub_name": "COE211 \u5de5\u7a0b\u6578\u5b78(\u4e00)", "scj_scr_mso": "\u5fc5\u4fee", "scr_precnt": 80.0, "year": 105, "semester": 1, "scr_selcode": "2015", "scr_credit": 3.0, "unt_ls": 4016, "scr_dup": "001", "scr_remarks": " ", "cls_name": "\u822a\u592a\u4e8c\u4e59", "sub_id": "02270", "scr_exambf": "\u5426", "cls_id": "CE13122", "scr_examid": "\u662f", "scr_examfn": "\u662f"}, "1052CM0114130636001": {"scr_period": "(\u4e94)06     \u555f\u57a3\u5ef3 \u6c5f\u6021\u84a8", "scr_acptcnt": 315.0, "sub_name": "UNIV909 \u6821\u5916\u5be6\u7fd2\u5c0e\u8ad6", "scj_scr_mso": "\u9078\u4fee", "scr_precnt": 380.0, "year": 105, "semester": 1, "scr_selcode": "0213", "scr_credit": 1.0, "unt_ls": 4102, "scr_dup": "001", "scr_remarks": "\u9650\u5546\u5b78\u9662\u5b78\u751f\u4fee\u8ab2", "cls_name": "\u4f01\u7ba1\u56db\u7532", "sub_id": "30636", "scr_exambf": "\u5426", "cls_id": "CM01141", "scr_examid": "\u5426", "scr_examfn": "\u5426"}, "1052CS0114170510001": {"scr_period": "(\u56db)02-04 \u7406413 \u674e\u82f1\u8c6a", "scr_acptcnt": 59.0, "sub_name": "MATH454 \u6a5f\u7387\u5c08\u984c", "scj_scr_mso": "\u9078\u4fee", "scr_precnt": 60.0, "year": 105, "semester": 1, "scr_selcode": "3001", "scr_credit": 3.0, "unt_ls": 4302, "scr_dup": "001", "scr_remarks": null, "cls_name": "\u61c9\u6578\u56db\u7532", "sub_id": "70510", "scr_exambf": "\u5426", "cls_id": "CS01141", "scr_examid": "\u5426", "scr_examfn": "\u5426"}, "1052CI0341076895001": {"scr_period": "(\u56db)11-13 \u8cc7\u96fb409 \u5289\u76ca\u745e", "scr_acptcnt": 10.0, "sub_name": "AUTO666 \u91ab\u5b78\u5f71\u50cf\u8a2d\u5099", "scj_scr_mso": "\u9078\u4fee", "scr_precnt": 10.0, "year": 105, "semester": 1, "scr_selcode": "1978", "scr_credit": 3.0, "unt_ls": 4506, "scr_dup": "001", "scr_remarks": null, "cls_name": "\u96fb\u901a\u535a\u4e00\u5b78\u4f4d\u5b78\u7a0b", "sub_id": "76895", "scr_exambf": "\u5426", "cls_id": "CI03410", "scr_examid": "\u5426", "scr_examfn": "\u5426"}, "1052CE0312143431001": {"scr_period": "(\u4e09)10-12 \u5fe0308 \u6797\u5efa\u69ae", "scr_acptcnt": 72.0, "sub_name": "ARCH238 \u73fe\u4ee3\u85dd\u8853\u53f2", "scj_scr_mso": "\u9078\u4fee", "scr_precnt": 60.0, "year": 105, "semester": 1, "scr_selcode": "1256", "scr_credit": 3.0, "unt_ls": 5002, "scr_dup": "001", "scr_remarks": null, "cls_name": "\u5efa\u7bc9\u4e8c\u7532\u5b78\u4f4d\u5b78\u7a0b", "sub_id": "43431", "scr_exambf": "\u5426", "cls_id": "CE03121", "scr_examid": "\u5426", "scr_examfn": "\u5426"}, "1052XD0110299250001": {"scr_period": "(\u4e00)01-02 \u672a\u6392\u6559\u5ba4 \u6797\u5fd7\u9060", "scr_acptcnt": 47.0, "sub_name": "ATHL234 \u9ad4\u80b2\uff0d\u9632\u8eab\u8853", "scj_scr_mso": "\u5fc5\u4fee", "scr_precnt": 50.0, "year": 105, "semester": 1, "scr_selcode": "3737", "scr_credit": 0.0, "unt_ls": 8888, "scr_dup": "001", "scr_remarks": "\u4e0a\u8ab2\u5730\u9ede\uff1a\u7b2c\u4e8c\u821e\u8e48\u5ba4(\u9ad4\u80b2\u9928\u4e8c\u6a13)", "cls_name": "\u9ad4\u80b2\u9078\u9805\u4e8c\u5e74\u7d1a", "sub_id": "99250", "scr_exambf": "\u5426", "cls_id": "XD01102", "scr_examid": "\u5426", "scr_examfn": "\u5426"}, "1052XD0110299250002": {"scr_period": "(\u4e00)03-04 \u672a\u6392\u6559\u5ba4 \u6797\u5fd7\u9060", "scr_acptcnt": 49.0, "sub_name": "ATHL234 \u9ad4\u80b2\uff0d\u9632\u8eab\u8853", "scj_scr_mso": "\u5fc5\u4fee", "scr_precnt": 50.0, "year": 105, "semester": 1, "scr_selcode": "3738", "scr_credit": 0.0, "unt_ls": 8888, "scr_dup": "002", "scr_remarks": "\u4e0a\u8ab2\u5730\u9ede\uff1a\u7b2c\u4e8c\u821e\u8e48\u5ba4(\u9ad4\u80b2\u9928\u4e8c\u6a13)", "cls_name": "\u9ad4\u80b2\u9078\u9805\u4e8c\u5e74\u7d1a", "sub_id": "99250", "scr_exambf": "\u5426", "cls_id": "XD01102", "scr_examid": "\u5426", "scr_examfn": "\u5426"}, "1052XD0110299250003": {"scr_period": "(\u56db)01-02 \u672a\u6392\u6559\u5ba4 \u9673\u57f9\u5b63", "scr_acptcnt": 50.0, "sub_name": "ATHL234 \u9ad4\u80b2\uff0d\u9632\u8eab\u8853", "scj_scr_mso": "\u5fc5\u4fee", "scr_precnt": 50.0, "year": 105, "semester": 1, "scr_selcode": "3739", "scr_credit": 0.0, "unt_ls": 8888, "scr_dup": "003", "scr_remarks": null, "cls_name": "\u9ad4\u80b2\u9078\u9805\u4e8c\u5e74\u7d1a", "sub_id": "99250", "scr_exambf": "\u5426", "cls_id": "XD01102", "scr_examid": "\u5426", "scr_examfn": "\u5426"}, "1052XF0711079874034": {"scr_period": "(\u4e94)00     \u672a\u6392\u6559\u5ba4 \u9673\u70af\u5fd7", "scr_acptcnt": 50.0, "sub_name": "GBIL110 \u8cc7\u8a0a\u7d20\u990a\u4f5c\u696d\u56db\uff1a\u5be6\u969b\u53c3\u8a2a\u5831\u544a", "scj_scr_mso": "\u5fc5\u4fee", "scr_precnt": 65.0, "year": 105, "semester": 1, "scr_selcode": "4368", "scr_credit": 0.0, "unt_ls": 8888, "scr_dup": "034", "scr_remarks": null, "cls_name": "\u6838\u5fc3\u5fc5\u4fee\u7d9c\u5408\u73ed", "sub_id": "79874", "scr_exambf": "\u5426", "cls_id": "XF07110", "scr_examid": "\u5426", "scr_examfn": "\u5426"}, "1052CE2311057550001": {"scr_period": "(\u56db)08-10 \u7d00105 \u9ec3\u667a\u5f65", "scr_acptcnt": 77.0, "sub_name": "UP203 \u7d93\u6fdf\u5b78", "scj_scr_mso": "\u5fc5\u4fee", "scr_precnt": 5.0, "year": 105, "semester": 1, "scr_selcode": "2126", "scr_credit": 3.0, "unt_ls": 4607, "scr_dup": "001", "scr_remarks": " ", "cls_name": "\u90fd\u8cc7\u4e00\u90fd\u5e02\u8a08\u756b\u7d44", "sub_id": "57550", "scr_exambf": "\u5426", "cls_id": "CE23110", "scr_examid": "\u5426", "scr_examfn": "\u662f"}, "1052XF0711079874032": {"scr_period": "(\u4e94)00     \u672a\u6392\u6559\u5ba4 \u9b4f\u5c11\u541b", "scr_acptcnt": 56.0, "sub_name": "GBIL110 \u8cc7\u8a0a\u7d20\u990a\u4f5c\u696d\u56db\uff1a\u5be6\u969b\u53c3\u8a2a\u5831\u544a", "scj_scr_mso": "\u5fc5\u4fee", "scr_precnt": 65.0, "year": 105, "semester": 1, "scr_selcode": "4366", "scr_credit": 0.0, "unt_ls": 8888, "scr_dup": "032", "scr_remarks": null, "cls_name": "\u6838\u5fc3\u5fc5\u4fee\u7d9c\u5408\u73ed", "sub_id": "79874", "scr_exambf": "\u5426", "cls_id": "XF07110", "scr_examid": "\u5426", "scr_examfn": "\u5426"}, "1052CI0084I60460001": {"scr_period": "(\u56db)08-09 \u8cc7\u96fbB02 (\u4e94)02     \u8cc7\u96fb107 \u9112\u6176\u798f", "scr_acptcnt": 18.0, "sub_name": "AUTO313 \u5fae\u50b3\u611f\u5668\u539f\u7406\u8207\u61c9\u7528", "scj_scr_mso": "\u9078\u4fee", "scr_precnt": 60.0, "year": 105, "semester": 1, "scr_selcode": "2498", "scr_credit": 3.0, "unt_ls": 4504, "scr_dup": "001", "scr_remarks": null, "cls_name": "\u751f\u91ab\u5de5\u7a0b\u5b78\u7a0b\u81ea\u63a7\u56db", "sub_id": "60460", "scr_exambf": "\u5426", "cls_id": "CI0084I", "scr_examid": "\u662f", "scr_examfn": "\u662f"}, "1052CE0113148242001": {"scr_period": "(\u4e8c)02-04 \u571f509 \u5ed6\u70ba\u5fe0", "scr_acptcnt": 60.0, "sub_name": "CE371 \u7d50\u69cb\u5b78(\u4e8c)", "scj_scr_mso": "\u5fc5\u4fee", "scr_precnt": 70.0, "year": 105, "semester": 1, "scr_selcode": "1104", "scr_credit": 3.0, "unt_ls": 4602, "scr_dup": "001", "scr_remarks": " ", "cls_name": "\u571f\u6728\u4e09\u7532", "sub_id": "48242", "scr_exambf": "\u5426", "cls_id": "CE01131", "scr_examid": "\u662f", "scr_examfn": "\u662f"}, "1052CI0083448590001": {"scr_period": "(\u4e8c)06-07 \u8cc7\u96fb404 (\u4e09)09     \u8cc7\u96fb404 \u9ec3\u6eaa\u6625", "scr_acptcnt": 82.0, "sub_name": "IECS321 \u7a0b\u5f0f\u8a9e\u8a00", "scj_scr_mso": "\u9078\u4fee", "scr_precnt": 90.0, "year": 105, "semester": 1, "scr_selcode": "2439", "scr_credit": 3.0, "unt_ls": 4501, "scr_dup": "001", "scr_remarks": null, "cls_name": "\u7db2\u969b\u7db2\u8def\u5b78\u7a0b\u8cc7\u8a0a\u4e09", "sub_id": "48590", "scr_exambf": "\u5426", "cls_id": "CI00834", "scr_examid": "\u662f", "scr_examfn": "\u662f"}, "1052CE0114175940001": {"scr_period": "(\u4e8c)01-02 \u571fB10 \u9ec3\u9038\u840d", "scr_acptcnt": 25.0, "sub_name": "CE427 \u908a\u5761\u7a69\u5b9a\u8207\u64cb\u571f\u7246", "scj_scr_mso": "\u9078\u4fee", "scr_precnt": 60.0, "year": 105, "semester": 1, "scr_selcode": "1129", "scr_credit": 2.0, "unt_ls": 4602, "scr_dup": "001", "scr_remarks": null, "cls_name": "\u571f\u6728\u56db\u7532", "sub_id": "75940", "scr_exambf": "\u5426", "cls_id": "CE01141", "scr_examid": "\u5426", "scr_examfn": "\u662f"}, "1052NM0211038550001": {"scr_period": "(\u4e00)06     \u4ebaB119A (\u4e09)02-04 \u4ebaB119A \u984f\u539a\u68df", "scr_acptcnt": 76.0, "sub_name": "ISTM110 \u500b\u9ad4\u7d93\u6fdf\u5b78", "scj_scr_mso": "\u5fc5\u4fee", "scr_precnt": 60.0, "year": 105, "semester": 1, "scr_selcode": "3335", "scr_credit": 4.0, "unt_ls": 4904, "scr_dup": "001", "scr_remarks": null, "cls_name": "\u5546\u5b78\u5275\u65b0\u4e00\u5b78\u4f4d\u5b78\u7a0b", "sub_id": "38550", "scr_exambf": "\u5426", "cls_id": "NM02110", "scr_examid": "\u662f", "scr_examfn": "\u5426"}, "1052CI0341052813001": {"scr_period": "(\u4e8c)02-04 \u96fb\u901a306 \u6d2a\u5b58\u4ec1", "scr_acptcnt": 11.0, "sub_name": "ELEN652 \u96fb\u6e90\u7ba1\u7406IC\u8a2d\u8a08", "scj_scr_mso": "\u9078\u4fee", "scr_precnt": 15.0, "year": 105, "semester": 1, "scr_selcode": "1842", "scr_credit": 3.0, "unt_ls": 4506, "scr_dup": "001", "scr_remarks": null, "cls_name": "\u96fb\u901a\u535a\u4e00\u5b78\u4f4d\u5b78\u7a0b", "sub_id": "52813", "scr_exambf": "\u5426", "cls_id": "CI03410", "scr_examid": "\u5426", "scr_examfn": "\u5426"}, "1052XE0110106855001": {"scr_period": "(\u4e94)11-12 \u5fe0308 \u6797\u9298\u5fb7,\u738b\u5efa\u96c4", "scr_acptcnt": 49.0, "sub_name": "GBCL102 \u516c\u6c11\u8996\u91ce", "scj_scr_mso": "\u5fc5\u4fee", "scr_precnt": 60.0, "year": 105, "semester": 1, "scr_selcode": "3786", "scr_credit": 2.0, "unt_ls": 8888, "scr_dup": "001", "scr_remarks": null, "cls_name": "\u7d9c\u5408\u73ed", "sub_id": "06855", "scr_exambf": "\u5426", "cls_id": "XE01101", "scr_examid": "\u5426", "scr_examfn": "\u5426"}, "1052CS0312202270001": {"scr_period": "(\u4e8c)10     \u5b78515 (\u56db)06-07 \u5b78515 \u90b1\u570b\u5cf0", "scr_acptcnt": 64.0, "sub_name": "SCI201 \u5de5\u7a0b\u6578\u5b78(\u4e00)", "scj_scr_mso": "\u5fc5\u4fee", "scr_precnt": 70.0, "year": 105, "semester": 1, "scr_selcode": "3137", "scr_credit": 3.0, "unt_ls": 4304, "scr_dup": "001", "scr_remarks": " ", "cls_name": "\u6750\u6599\u4e8c\u4e59", "sub_id": "02270", "scr_exambf": "\u5426", "cls_id": "CS03122", "scr_examid": "\u662f", "scr_examfn": "\u662f"}, "1052CB0713243034001": {"scr_period": "(\u56db)08-09 \u8a9e303 \u5ed6\u73ee\u73c8", "scr_acptcnt": 49.0, "sub_name": "GBEN101 \u5c08\u696d\u5916\u8a9e", "scj_scr_mso": "\u5fc5\u4fee", "scr_precnt": 60.0, "year": 105, "semester": 1, "scr_selcode": "0554", "scr_credit": 2.0, "unt_ls": 4105, "scr_dup": "001", "scr_remarks": " ", "cls_name": "\u7d71\u8a08\u4e09\u4e59", "sub_id": "43034", "scr_exambf": "\u5426", "cls_id": "CB07132", "scr_examid": "\u5426", "scr_examfn": "\u5426"}, "1052PC3510097500002": {"scr_period": "(\u4e8c)08-09 \u8cc7\u96fb410 \u6590\u514b\u79ae", "scr_acptcnt": 51.0, "sub_name": "LC111 \u6cd5\u6587(\u4e00)", "scj_scr_mso": "\u9078\u4fee", "scr_precnt": 60.0, "year": 105, "semester": 1, "scr_selcode": "3433", "scr_credit": 2.0, "unt_ls": 8888, "scr_dup": "002", "scr_remarks": "\u4fee\u7fd2\u53ca\u9078\u8ab2\u65b9\u5f0f\u540c\u4e0a\u3002\u958b\u653e\u5168\u6821\u5404\u5e74\u7d1a\u5b78\u751f\u4fee\u7fd2\u3002\u50c5\u958b\u653e9\u670812\u65e5\u524d\u7db2\u8def\u52a0\u9000\u9078\u3002\u958b\u5b78\u7b2c\u4e00\u6b21\u4e0a\u8ab2\uff0c\u8001\u5e2b\u6191\u7c3d\u5230\u55ae\u9ede\u540d\u3002", "cls_name": "\u61c9\u7528\u5916\u8a9e\u5b78\u7a0b", "sub_id": "97500", "scr_exambf": "\u5426", "cls_id": "PC35100", "scr_examid": "\u5426", "scr_examfn": "\u5426"}, "1052CB0512145750001": {"scr_period": "(\u4e09)02-04 \u5546402 \u9ad8\u79c0\u862d", "scr_acptcnt": 62.0, "sub_name": "STAT101 \u7d71\u8a08\u5b78(\u4e00)", "scj_scr_mso": "\u5fc5\u4fee", "scr_precnt": 72.0, "year": 105, "semester": 1, "scr_selcode": "0421", "scr_credit": 3.0, "unt_ls": 4104, "scr_dup": "001", "scr_remarks": " ", "cls_name": "\u8ca1\u7a05\u4e8c\u7532", "sub_id": "45750", "scr_exambf": "\u5426", "cls_id": "CB05121", "scr_examid": "\u662f", "scr_examfn": "\u662f"}, "1052PC3510097500001": {"scr_period": "(\u4e8c)03-04 \u8cc7\u96fbB07 \u6590\u514b\u79ae", "scr_acptcnt": 56.0, "sub_name": "LC111 \u6cd5\u6587(\u4e00)", "scj_scr_mso": "\u9078\u4fee", "scr_precnt": 60.0, "year": 105, "semester": 1, "scr_selcode": "3432", "scr_credit": 2.0, "unt_ls": 8888, "scr_dup": "001", "scr_remarks": "\u9650\u4e00\u3001\u4e8c\u3001\u4e09\u5e74\u7d1a\u5b78\u751f\u4fee\u7fd2\u3002        \u50c5\u958b\u653e9\u670812\u65e5\u524d\u7db2\u8def\u52a0\u9000\u9078\u3002           \u958b\u5b78\u7b2c\u4e00\u6b21\u4e0a\u8ab2\uff0c\u8001\u5e2b\u6191\u7c3d\u5230\u55ae\u9ede\u540d\u3002", "cls_name": "\u61c9\u7528\u5916\u8a9e\u5b78\u7a0b", "sub_id": "97500", "scr_exambf": "\u5426", "cls_id": "PC35100", "scr_examid": "\u5426", "scr_examfn": "\u5426"}, "1052CB1453237750001": {"scr_period": "(\u4e8c)11-13 \u5546406 \u8449\u4fd0\u5ef7", "scr_acptcnt": 46.0, "sub_name": "FINA234 \u8ca1\u52d9\u7ba1\u7406", "scj_scr_mso": "\u5fc5\u4fee", "scr_precnt": 70.0, "year": 105, "semester": 1, "scr_selcode": "0744", "scr_credit": 3.0, "unt_ls": 4110, "scr_dup": "001", "scr_remarks": " ", "cls_name": "\u5546\u5b78\u9032\u4fee\u4e09\u4e59", "sub_id": "37750", "scr_exambf": "\u5426", "cls_id": "CB14532", "scr_examid": "\u5426", "scr_examfn": "\u5426"}, "1052CE2312044200001": {"scr_period": "(\u4e09)03-04 \u7d00111 \u9ad8\u8c6b\u9e92", "scr_acptcnt": 68.0, "sub_name": "UP324 \u6e2c\u91cf\u5b78\u5be6\u7fd2", "scj_scr_mso": "\u5fc5\u4fee", "scr_precnt": 60.0, "year": 105, "semester": 1, "scr_selcode": "2134", "scr_credit": 0.0, "unt_ls": 4607, "scr_dup": "001", "scr_remarks": " ", "cls_name": "\u90fd\u8cc7\u4e8c\u90fd\u5e02\u8a08\u756b\u7d44", "sub_id": "44200", "scr_exambf": "\u5426", "cls_id": "CE23120", "scr_examid": "\u5426", "scr_examfn": "\u5426"}, "1052CM0214159052001": {"scr_period": "(\u516d)06-08 \u672a\u6392\u6559\u5ba4 \u6797\u4f69\u5100,\u9673\u65b9\u5143", "scr_acptcnt": 39.0, "sub_name": "TTEM491 \u904b\u8f38\u7ba1\u7406\u5be6\u52d9\u5be6\u7fd2", "scj_scr_mso": "\u9078\u4fee", "scr_precnt": 60.0, "year": 105, "semester": 1, "scr_selcode": "2822", "scr_credit": 3.0, "unt_ls": 4606, "scr_dup": "001", "scr_remarks": null, "cls_name": "\u904b\u7ba1\u56db\u7532", "sub_id": "59052", "scr_exambf": "\u5426", "cls_id": "CM02141", "scr_examid": "\u5426", "scr_examfn": "\u5426"}, "1052CE0531036960001": {"scr_period": "(\u56db)07     \u5de5410 \u9ec3\u5efa\u9716", "scr_acptcnt": 27.0, "sub_name": "FCME683 \u66f8\u5831\u8a0e\u8ad6(\u4e00)", "scj_scr_mso": "\u5fc5\u4fee", "scr_precnt": 30.0, "year": 105, "semester": 1, "scr_selcode": "1508", "scr_credit": 1.0, "unt_ls": 4008, "scr_dup": "001", "scr_remarks": " ", "cls_name": "\u7e96\u8907\u78a9\u4e00", "sub_id": "36960", "scr_exambf": "\u5426", "cls_id": "CE05310", "scr_examid": "\u5426", "scr_examfn": "\u5426"}, "1052CB0214237080001": {"scr_period": "(\u4e94)02-04 \u5546405 \u7f85\u6176\u9f8d", "scr_acptcnt": 16.0, "sub_name": "ITRA452 \u5831\u95dc\u696d\u52d9\u7d93\u71df", "scj_scr_mso": "\u9078\u4fee", "scr_precnt": 70.0, "year": 105, "semester": 1, "scr_selcode": "0215", "scr_credit": 3.0, "unt_ls": 4103, "scr_dup": "001", "scr_remarks": null, "cls_name": "\u570b\u8cbf\u56db\u4e59", "sub_id": "37080", "scr_exambf": "\u5426", "cls_id": "CB02142", "scr_examid": "\u662f", "scr_examfn": "\u5426"}, "1052CS0311248560001": {"scr_period": "(\u4e09)06-07 \u7406409 (\u4e94)01-02 \u7406313 \u674e\u8cdc\u798f", "scr_acptcnt": 58.0, "sub_name": "PHYS105 \u666e\u901a\u7269\u7406(\u4e00)", "scj_scr_mso": "\u5fc5\u4fee", "scr_precnt": 8.0, "year": 105, "semester": 1, "scr_selcode": "3121", "scr_credit": 3.0, "unt_ls": 4304, "scr_dup": "001", "scr_remarks": " ", "cls_name": "\u6750\u6599\u4e00\u4e59", "sub_id": "48560", "scr_exambf": "\u5426", "cls_id": "CS03112", "scr_examid": "\u662f", "scr_examfn": "\u662f"}, "1052CE0512177008001": {"scr_period": "(\u4e09)06-07 \u5de5416 \u9673\u81f4\u5149", "scr_acptcnt": 64.0, "sub_name": "FCME234 \u7e96\u7dad\u5316\u5b78(\u4e00)", "scj_scr_mso": "\u5fc5\u4fee", "scr_precnt": 65.0, "year": 105, "semester": 1, "scr_selcode": "1461", "scr_credit": 2.0, "unt_ls": 4008, "scr_dup": "001", "scr_remarks": " ", "cls_name": "\u7e96\u8907\u4e8c\u7532", "sub_id": "77008", "scr_exambf": "\u5426", "cls_id": "CE05121", "scr_examid": "\u662f", "scr_examfn": "\u662f"}, "1052CE1212154460001": {"scr_period": "(\u4e00)08-10 \u8cc7\u96fb502 \u5f35\u8208\u653f", "scr_acptcnt": 71.0, "sub_name": "AUTO205 \u96fb\u5b50\u5b78\u5be6\u9a57(\u4e00)", "scj_scr_mso": "\u5fc5\u4fee", "scr_precnt": 66.0, "year": 105, "semester": 1, "scr_selcode": "1954", "scr_credit": 1.0, "unt_ls": 4504, "scr_dup": "001", "scr_remarks": " ", "cls_name": "\u81ea\u63a7\u4e8c\u7532", "sub_id": "54460", "scr_exambf": "\u5426", "cls_id": "CE12121", "scr_examid": "\u5426", "scr_examfn": "\u5426"}, "1052CM0114230636001": {"scr_period": "(\u4e94)06     \u555f\u57a3\u5ef3 \u6c5f\u6021\u84a8", "scr_acptcnt": 315.0, "sub_name": "UNIV909 \u6821\u5916\u5be6\u7fd2\u5c0e\u8ad6", "scj_scr_mso": "\u9078\u4fee", "scr_precnt": 380.0, "year": 105, "semester": 1, "scr_selcode": "0213", "scr_credit": 1.0, "unt_ls": 4102, "scr_dup": "001", "scr_remarks": "\u9650\u5546\u5b78\u9662\u5b78\u751f\u4fee\u8ab2", "cls_name": "\u4f01\u7ba1\u56db\u4e59", "sub_id": "30636", "scr_exambf": "\u5426", "cls_id": "CM01142", "scr_examid": "\u5426", "scr_examfn": "\u5426"}, "1052CS0614208354001": {"scr_period": "(\u4e8c)08-10 \u7406B13 \u76e7\u8056\u83ef", "scr_acptcnt": 17.0, "sub_name": "OPT482 \u5149\u5b78\u5143\u4ef6\u88fd\u4f5c\u5c08\u984c\u5be6\u4f5c", "scj_scr_mso": "\u9078\u4fee", "scr_precnt": 40.0, "year": 105, "semester": 1, "scr_selcode": "3314", "scr_credit": 1.0, "unt_ls": 4306, "scr_dup": "001", "scr_remarks": "\u672c\u8ab2\u7a0b\u70ba\u7d42\u7aef\u8ab2\u7a0b\uff0c\u4e26\u4e0d\u63a5\u53d7\u7cfb\u5916\u540c\u5b78\u9078\u4fee\u3002", "cls_name": "\u5149\u96fb\u56db\u4e59", "sub_id": "08354", "scr_exambf": "\u5426", "cls_id": "CS06142", "scr_examid": "\u5426", "scr_examfn": "\u5426"}, "1052CE0211100161001": {"scr_period": "(\u56db)06-07 \u672a\u6392\u6559\u5ba4 \u5f35\u5b9c\u6b63", "scr_acptcnt": 46.0, "sub_name": "ATHL101 \u9ad4\u80b2(\u4e00)", "scj_scr_mso": "\u5fc5\u4fee", "scr_precnt": 6.0, "year": 105, "semester": 1, "scr_selcode": "1150", "scr_credit": 0.0, "unt_ls": 4603, "scr_dup": "001", "scr_remarks": " ", "cls_name": "\u6c34\u5229\u8207\u8cc7\u4fdd\u4e00\u7532", "sub_id": "00161", "scr_exambf": "\u5426", "cls_id": "CE02111", "scr_examid": "\u5426", "scr_examfn": "\u5426"}, "1052CI0083J65110001": {"scr_period": "(\u4e00)04     \u8cc7\u96fb108 (\u4e09)06-07 \u8cc7\u96fb306 \u6797\u5b97\u5fd7", "scr_acptcnt": 37.0, "sub_name": "ELEN302 \u8907\u8b8a\u51fd\u6578", "scj_scr_mso": "\u9078\u4fee", "scr_precnt": 60.0, "year": 105, "semester": 1, "scr_selcode": "2465", "scr_credit": 3.0, "unt_ls": 4502, "scr_dup": "001", "scr_remarks": null, "cls_name": "\u534a\u5c0e\u9ad4\u96fb\u5b50\u5b78\u7a0b\u96fb\u5b50\u4e09", "sub_id": "65110", "scr_exambf": "\u5426", "cls_id": "CI0083J", "scr_examid": "\u5426", "scr_examfn": "\u5426"}, "1052CE0314200001001": {"scr_period": "(\u56db)06     \u8a9e202 \u675c\u65b9\u4e2d", "scr_acptcnt": 49.0, "sub_name": "UNIV902 \u73ed\u7d1a\u6d3b\u52d5", "scj_scr_mso": "\u5fc5\u4fee", "scr_precnt": 60.0, "year": 105, "semester": 1, "scr_selcode": "1277", "scr_credit": 0.0, "unt_ls": 5002, "scr_dup": "001", "scr_remarks": " ", "cls_name": "\u5efa\u7bc9\u56db\u4e59\u5b78\u4f4d\u5b78\u7a0b", "sub_id": "00001", "scr_exambf": "\u5426", "cls_id": "CE03142", "scr_examid": "\u5426", "scr_examfn": "\u5426"}, "1052XH0111113891023": {"scr_period": "(\u4e09)03-04 \u5fe0305 \u9ec3\u5409\u76ca,\u6797\u6b63\u5fe0", "scr_acptcnt": 106.0, "sub_name": "MILT121 \u5168\u6c11\u570b\u9632\u6559\u80b2\u8ecd\u4e8b\u8a13\u7df4(\u4e00)", "scj_scr_mso": "\u5fc5\u4fee", "scr_precnt": 120.0, "year": 105, "semester": 1, "scr_selcode": "4394", "scr_credit": 0.0, "unt_ls": 8888, "scr_dup": "023", "scr_remarks": "\u672c\u8ab2\u7a0b\u9700\u5be6\u65bd\u8cc7\u8a0a\u7d20\u990a--\u5371\u6a5f\u8655\u7406\u8ab2\u7a0b   \uff0c\u8acb\u91cd\u88dc\u4fee\u751f\u638c\u63e1\u76f8\u95dc\u9078\u8ab2\u8a0a\u606f", "cls_name": "\u8ecd\u8a13(\u4e00\u5e74\u7d1a)", "sub_id": "13891", "scr_exambf": "\u5426", "cls_id": "XH01111", "scr_examid": "\u5426", "scr_examfn": "\u5426"}, "1052CF0131A22910001": {"scr_period": "(\u65e5)06-08 \u55461009 \u5442\u745e\u79cb", "scr_acptcnt": 22.0, "sub_name": "FINA600 \u91d1\u878d\u6a5f\u69cb\u7d93\u71df\u8207\u7ba1\u7406", "scj_scr_mso": "\u9078\u4fee", "scr_precnt": 25.0, "year": 105, "semester": 1, "scr_selcode": "2228", "scr_credit": 3.0, "unt_ls": 4804, "scr_dup": "001", "scr_remarks": null, "cls_name": "\u91d1\u878d\u5c08\u73ed\u78a9\u4e00", "sub_id": "22910", "scr_exambf": "\u5426", "cls_id": "CF0131A", "scr_examid": "\u5426", "scr_examfn": "\u662f"}, "1052CI0831K33030001": {"scr_period": "(\u4e94)02-04 \u8cc7\u96fb311 \u5f35\u8cb4\u5fe0", "scr_acptcnt": 25.0, "sub_name": "IECS623 \u9ad8\u7b49\u8a08\u7b97\u6a5f\u7d50\u69cb", "scj_scr_mso": "\u9078\u4fee", "scr_precnt": 35.0, "year": 105, "semester": 1, "scr_selcode": "1687", "scr_credit": 3.0, "unt_ls": 4509, "scr_dup": "001", "scr_remarks": null, "cls_name": "\u901a\u8a0a\u8207IC\u5c08\u73ed\u78a9\u4e00", "sub_id": "33030", "scr_exambf": "\u5426", "cls_id": "CI0831K", "scr_examid": "\u5426", "scr_examfn": "\u5426"}, "1052XD0110299110011": {"scr_period": "(\u4e94)06-07 \u672a\u6392\u6559\u5ba4 \u8a31\u5bb6\u5f97", "scr_acptcnt": 57.0, "sub_name": "ATHL219 \u9ad4\u80b2\uff0d\u786c\u5f0f\u7db2\u7403", "scj_scr_mso": "\u5fc5\u4fee", "scr_precnt": 60.0, "year": 105, "semester": 1, "scr_selcode": "3714", "scr_credit": 0.0, "unt_ls": 8888, "scr_dup": "011", "scr_remarks": "\u4e0a\u8ab2\u5730\u9ede\uff1a\u7db2\u7403\u5834", "cls_name": "\u9ad4\u80b2\u9078\u9805\u4e8c\u5e74\u7d1a", "sub_id": "99110", "scr_exambf": "\u5426", "cls_id": "XD01102", "scr_examid": "\u5426", "scr_examfn": "\u5426"}, "1052CB1451231255001": {"scr_period": "(\u4e94)11-12 \u884c\u653f\u4e8c\u9928205(\u8996\u807d\u5ba4) \u738b\u6f22\u6c11,\u9ad8\u60e0\u677e", "scr_acptcnt": 128.0, "sub_name": "BCE103 \u5546\u5b78\u6982\u8ad6", "scj_scr_mso": "\u5fc5\u4fee", "scr_precnt": 111.0, "year": 105, "semester": 1, "scr_selcode": "0714", "scr_credit": 2.0, "unt_ls": 4110, "scr_dup": "001", "scr_remarks": null, "cls_name": "\u5546\u5b78\u9032\u4fee\u4e00\u4e59", "sub_id": "31255", "scr_exambf": "\u5426", "cls_id": "CB14512", "scr_examid": "\u5426", "scr_examfn": "\u5426"}, "1052CB0211260520001": {"scr_period": "(\u56db)08-10 \u8a9e103 \u694a\u61ff\u6dd1", "scr_acptcnt": 62.0, "sub_name": "MATH105 \u5fae\u7a4d\u5206(\u4e00)", "scj_scr_mso": "\u5fc5\u4fee", "scr_precnt": 8.0, "year": 105, "semester": 1, "scr_selcode": "0137", "scr_credit": 3.0, "unt_ls": 4103, "scr_dup": "001", "scr_remarks": " ", "cls_name": "\u570b\u8cbf\u4e00\u4e59", "sub_id": "60520", "scr_exambf": "\u5426", "cls_id": "CB02112", "scr_examid": "\u662f", "scr_examfn": "\u662f"}, "1052CB0313322740001": {"scr_period": "(\u56db)02-04 \u5546203 \u6d2a\u5049\u5cf0", "scr_acptcnt": 66.0, "sub_name": "FINA200 \u91d1\u878d\u5e02\u5834", "scj_scr_mso": "\u5fc5\u4fee", "scr_precnt": 80.0, "year": 105, "semester": 1, "scr_selcode": "0295", "scr_credit": 3.0, "unt_ls": 4801, "scr_dup": "001", "scr_remarks": " ", "cls_name": "\u8ca1\u91d1\u4e09\u4e19", "sub_id": "22740", "scr_exambf": "\u5426", "cls_id": "CB03133", "scr_examid": "\u662f", "scr_examfn": "\u662f"}, "1052CH0613250973001": {"scr_period": "(\u4e8c)06-07 \u4eba505 \u5b89\u99ac\u4e01", "scr_acptcnt": 37.0, "sub_name": "FLL033 \u7b2c\u4e8c\u5916\u8a9e\uff08\u4e09\uff09-\u5fb7\u6587", "scj_scr_mso": "\u5fc5\u4fee", "scr_precnt": 50.0, "year": 105, "semester": 1, "scr_selcode": "2343", "scr_credit": 2.0, "unt_ls": 4406, "scr_dup": "001", "scr_remarks": null, "cls_name": "\u5916\u6587\u4e09\u4e59", "sub_id": "50973", "scr_exambf": "\u5426", "cls_id": "CH06132", "scr_examid": "\u5426", "scr_examfn": "\u5426"}, "1052CB1531212990001": {"scr_period": "(\u4e94)03     \u884c\u653f\u4e8c\u9928205(\u8996\u807d\u5ba4) \u984f\u539a\u68df", "scr_acptcnt": 117.0, "sub_name": "COB606 \u4f01\u696d\u502b\u7406\u8207\u793e\u6703\u8cac\u4efb\u8b1b\u5ea7(\u4e00)", "scj_scr_mso": "\u9078\u4fee", "scr_precnt": 100.0, "year": 105, "semester": 1, "scr_selcode": "0648", "scr_credit": 1.0, "unt_ls": 4111, "scr_dup": "001", "scr_remarks": " ", "cls_name": "\u8ca1\u6cd5\u78a9\u4e00\u6cd5\u5f8b\u5c08\u696d\u7d44", "sub_id": "12990", "scr_exambf": "\u5426", "cls_id": "CB15312", "scr_examid": "\u5426", "scr_examfn": "\u5426"}, "1052CB0214143005001": {"scr_period": "(\u56db)11-13 \u5546206 \u6881\u99a8\u4e88,\u97d3\u5b9c,\u5289\u7fc1\u6606", "scr_acptcnt": 71.0, "sub_name": "ITRA352 \u570b\u969b\u8cbf\u6613\u7d93\u71df\u7ba1\u7406", "scj_scr_mso": "\u5fc5\u4fee", "scr_precnt": 60.0, "year": 105, "semester": 1, "scr_selcode": "0206", "scr_credit": 3.0, "unt_ls": 4103, "scr_dup": "001", "scr_remarks": "\u570b\u8cbf\u7cfb\u7d42\u7aef\u8ab2\u7a0b,\u9650\u570b\u8cbf\u7cfb\u5b78\u751f\u53ca\u8f14\u7cfb\u96d9\u4e3b\u4fee\u5b78\u751f\u4fee\u8ab2", "cls_name": "\u570b\u8cbf\u56db\u7532", "sub_id": "43005", "scr_exambf": "\u5426", "cls_id": "CB02141", "scr_examid": "\u5426", "scr_examfn": "\u5426"}, "1052CB2513122744001": {"scr_period": "(\u4e8c)08-10 \u5efa305 \u9673\u74ca\u601c", "scr_acptcnt": 20.0, "sub_name": "BIBA323 \u91d1\u878d\u5e02\u5834\u5c0e\u8ad6", "scj_scr_mso": "\u9078\u4fee", "scr_precnt": 60.0, "year": 105, "semester": 1, "scr_selcode": "0866", "scr_credit": 3.0, "unt_ls": 4115, "scr_dup": "001", "scr_remarks": null, "cls_name": "\u570b\u4f01\u4e09\u7532\u5b78\u4f4d\u5b78\u7a0b", "sub_id": "22744", "scr_exambf": "\u5426", "cls_id": "CB25131", "scr_examid": "\u5426", "scr_examfn": "\u5426"}, "1052CM0113111241001": {"scr_period": "(\u4e8c)11-13 \u79d1\u822a205 \u5289\u5e73\u6587", "scr_acptcnt": 84.0, "sub_name": "MGT374 \u6587\u5316\u5275\u610f\u7522\u696d\u7ba1\u7406", "scj_scr_mso": "\u9078\u4fee", "scr_precnt": 88.0, "year": 105, "semester": 1, "scr_selcode": "2710", "scr_credit": 3.0, "unt_ls": 4102, "scr_dup": "001", "scr_remarks": " ", "cls_name": "\u4f01\u7ba1\u4e09\u7532", "sub_id": "11241", "scr_exambf": "\u5426", "cls_id": "CM01131", "scr_examid": "\u5426", "scr_examfn": "\u5426"}, "1052CE0112219550001": {"scr_period": "(\u56db)07-09 \u571f403 \u535c\u541b\u5e73", "scr_acptcnt": 75.0, "sub_name": "CE278 \u6750\u6599\u529b\u5b78", "scj_scr_mso": "\u5fc5\u4fee", "scr_precnt": 70.0, "year": 105, "semester": 1, "scr_selcode": "1095", "scr_credit": 3.0, "unt_ls": 4602, "scr_dup": "001", "scr_remarks": " ", "cls_name": "\u571f\u6728\u4e8c\u4e59", "sub_id": "19550", "scr_exambf": "\u5426", "cls_id": "CE01122", "scr_examid": "\u662f", "scr_examfn": "\u662f"}, "1052CM0231027162001": {"scr_period": "(\u4e00)04     \u7d00412 \u6797\u7e7c\u660c", "scr_acptcnt": 18.0, "sub_name": "CCD685 \u82f1\u6587\u66f8\u5831\u8a0e\u8ad6(\u4e00)", "scj_scr_mso": "\u5fc5\u4fee", "scr_precnt": 20.0, "year": 105, "semester": 1, "scr_selcode": "2824", "scr_credit": 1.0, "unt_ls": 4606, "scr_dup": "001", "scr_remarks": " ", "cls_name": "\u904b\u7ba1\u78a9\u4e00", "sub_id": "27162", "scr_exambf": "\u5426", "cls_id": "CM02310", "scr_examid": "\u5426", "scr_examfn": "\u5426"}, "1052XC01132GM205001": {"scr_period": "(\u56db)06-07 \u4eba704 \u5b8b\u660e\u5f18", "scr_acptcnt": 32.0, "sub_name": "GMII301 \u521d\u968e\u667a\u6167\u578b\u5275\u65b0", "scj_scr_mso": "\u9078\u4fee", "scr_precnt": 40.0, "year": 105, "semester": 1, "scr_selcode": "3602", "scr_credit": 2.0, "unt_ls": 8888, "scr_dup": "001", "scr_remarks": "\u662f\u5426\u5217\u5165\u7562\u696d\u5b78\u5206\u8acb\u81f3\u5404\u7cfb\u78ba\u8a8d\u3002\u8a73\u60c5  \u8acb\u53c3\u95b1\u300c\u901a\u8b58\u8ab2\u7a0b\u9078\u8ab2\u9808\u77e5\u300d\u3002\u7d71\u5408\u985e\u8ab2  \u7a0b\u4e0d\u5f97\u8f49\u8a8d\u5217\u70ba\u4eba\u6587\u3001\u793e\u6703\u6216\u81ea\u7136\u9818\u57df\u8ab2  \u7a0b\u3002", "cls_name": "\u901a\u8b58\uff0d\u7d71\u5408(M)", "sub_id": "GM205", "scr_exambf": "\u5426", "cls_id": "XC01132", "scr_examid": "\u5426", "scr_examfn": "\u5426"}, "1052CE0511227400001": {"scr_period": "(\u4e00)03     \u5de5302 (\u4e00)04     \u571f302(\u96fb\u8166\u5be6\u7fd2\u5ba4) \u674e\u7dad\u5e73", "scr_acptcnt": 59.0, "sub_name": "COE110 \u8a08\u7b97\u6a5f\u6982\u8ad6", "scj_scr_mso": "\u5fc5\u4fee", "scr_precnt": 5.0, "year": 105, "semester": 1, "scr_selcode": "1446", "scr_credit": 2.0, "unt_ls": 4008, "scr_dup": "001", "scr_remarks": " ", "cls_name": "\u7e96\u8907\u4e00\u4e59", "sub_id": "27400", "scr_exambf": "\u5426", "cls_id": "CE05112", "scr_examid": "\u662f", "scr_examfn": "\u662f"}, "1052CM0212163150001": {"scr_period": "(\u4e09)07-09 \u7d00209A \u6797\u7e7c\u660c", "scr_acptcnt": 58.0, "sub_name": "TTEM299 \u7ba1\u7406\u6578\u5b78", "scj_scr_mso": "\u5fc5\u4fee", "scr_precnt": 60.0, "year": 105, "semester": 1, "scr_selcode": "2773", "scr_credit": 3.0, "unt_ls": 4606, "scr_dup": "001", "scr_remarks": " ", "cls_name": "\u904b\u7ba1\u4e8c\u7532", "sub_id": "63150", "scr_exambf": "\u5426", "cls_id": "CM02121", "scr_examid": "\u662f", "scr_examfn": "\u662f"}, "1052XH0111113891021": {"scr_period": "(\u4e09)06-07 \u8cc7\u96fbB22(\u8996\u807d\u5ba4) \u6797\u6b63\u5fe0,\u738b\u91d1\u8f1d", "scr_acptcnt": 104.0, "sub_name": "MILT121 \u5168\u6c11\u570b\u9632\u6559\u80b2\u8ecd\u4e8b\u8a13\u7df4(\u4e00)", "scj_scr_mso": "\u5fc5\u4fee", "scr_precnt": 120.0, "year": 105, "semester": 1, "scr_selcode": "4392", "scr_credit": 0.0, "unt_ls": 8888, "scr_dup": "021", "scr_remarks": "\u672c\u8ab2\u7a0b\u9700\u5be6\u65bd\u8cc7\u8a0a\u7d20\u990a--\u5371\u6a5f\u8655\u7406\u8ab2\u7a0b   \uff0c\u8acb\u91cd\u88dc\u4fee\u751f\u638c\u63e1\u76f8\u95dc\u9078\u8ab2\u8a0a\u606f", "cls_name": "\u8ecd\u8a13(\u4e00\u5e74\u7d1a)", "sub_id": "13891", "scr_exambf": "\u5426", "cls_id": "XH01111", "scr_examid": "\u5426", "scr_examfn": "\u5426"}, "1052CE2211063891001": {"scr_period": "(\u4e8c)06-08 \u8cc7\u96fb125(\u96fb\u8166\u5be6\u7fd2\u5ba4) \u8f9c\u6587\u5143", "scr_acptcnt": 49.0, "sub_name": "SI241 \u7db2\u969b\u7db2\u8def\u5730\u7406\u8cc7\u8a0a\u7cfb\u7d71", "scj_scr_mso": "\u9078\u4fee", "scr_precnt": 5.0, "year": 105, "semester": 1, "scr_selcode": "2093", "scr_credit": 3.0, "unt_ls": 4607, "scr_dup": "001", "scr_remarks": null, "cls_name": "\u90fd\u8cc7\u4e00\u7a7a\u9593\u8cc7\u8a0a\u7d44", "sub_id": "63891", "scr_exambf": "\u5426", "cls_id": "CE22110", "scr_examid": "\u5426", "scr_examfn": "\u5426"}, "1052CB0712146280001": {"scr_period": "(\u4e94)02-04 \u7d00207(\u96fb\u8166\u5be6\u7fd2\u5ba4) \u738b\u5a49\u502b", "scr_acptcnt": 72.0, "sub_name": "STAT413 \u7d71\u8a08\u8a08\u7b97", "scj_scr_mso": "\u5fc5\u4fee", "scr_precnt": 90.0, "year": 105, "semester": 1, "scr_selcode": "0529", "scr_credit": 3.0, "unt_ls": 4105, "scr_dup": "001", "scr_remarks": " ", "cls_name": "\u7d71\u8a08\u4e8c\u7532", "sub_id": "46280", "scr_exambf": "\u5426", "cls_id": "CB07121", "scr_examid": "\u5426", "scr_examfn": "\u5426"}, "1052CB0213326178001": {"scr_period": "(\u4e94)07-09 \u5546206 \u5ed6\u555f\u7db1", "scr_acptcnt": 81.0, "sub_name": "ITRA374 \u6771\u4e9e\u53f0\u5546\u8207\u570b\u969b\u653f\u6cbb\u7d93\u6fdf", "scj_scr_mso": "\u9078\u4fee", "scr_precnt": 80.0, "year": 105, "semester": 1, "scr_selcode": "0198", "scr_credit": 3.0, "unt_ls": 4103, "scr_dup": "001", "scr_remarks": null, "cls_name": "\u570b\u8cbf\u4e09\u4e19", "sub_id": "26178", "scr_exambf": "\u5426", "cls_id": "CB02133", "scr_examid": "\u5426", "scr_examfn": "\u5426"}, "1052XF0311057551016": {"scr_period": "(\u4e94)02-04 \u5546205 \u90ed\u7950\u8aa0", "scr_acptcnt": 69.0, "sub_name": "ECON101 \u7d93\u6fdf\u5b78(\u4e00)", "scj_scr_mso": "\u5fc5\u4fee", "scr_precnt": 123.0, "year": 105, "semester": 1, "scr_selcode": "4093", "scr_credit": 3.0, "unt_ls": 8888, "scr_dup": "016", "scr_remarks": "\u9808\u96a8\u73ed\u4fee\u7fd2\u9078\u8ab2\u4ee3\u865f4110\u300c\u7d93\u6fdf\u5b78(\u4e00)\u5be6\u7fd2\u300d\u8ab2\u3002", "cls_name": "\u7d93\u6fdf\u5b78\u7d9c\u5408\u73ed", "sub_id": "57551", "scr_exambf": "\u5426", "cls_id": "XF03110", "scr_examid": "\u662f", "scr_examfn": "\u662f"}, "1052CB0514241640001": {"scr_period": "(\u56db)06-08 \u5546404 \u6d2a\u570b\u4ec1", "scr_acptcnt": 54.0, "sub_name": "PF452 \u570b\u969b\u79df\u7a05", "scj_scr_mso": "\u5fc5\u4fee", "scr_precnt": 60.0, "year": 105, "semester": 1, "scr_selcode": "0451", "scr_credit": 3.0, "unt_ls": 4104, "scr_dup": "001", "scr_remarks": " ", "cls_name": "\u8ca1\u7a05\u56db\u4e59", "sub_id": "41640", "scr_exambf": "\u5426", "cls_id": "CB05142", "scr_examid": "\u5426", "scr_examfn": "\u5426"}, "1052CE1213266301001": {"scr_period": "(\u4e8c)01-02 \u5fe0207 (\u56db)04     \u5fe0B03 \u8607\u6587\u5f6c", "scr_acptcnt": 85.0, "sub_name": "AUTO300 \u7dda\u6027\u63a7\u5236\u7cfb\u7d71(\u4e00)", "scj_scr_mso": "\u5fc5\u4fee", "scr_precnt": 80.0, "year": 105, "semester": 1, "scr_selcode": "1965", "scr_credit": 3.0, "unt_ls": 4504, "scr_dup": "001", "scr_remarks": " ", "cls_name": "\u81ea\u63a7\u4e09\u4e59", "sub_id": "66301", "scr_exambf": "\u5426", "cls_id": "CE12132", "scr_examid": "\u662f", "scr_examfn": "\u662f"}, "1052CE0211148560001": {"scr_period": "(\u4e09)08-09 \u8a9e103 \u65b9\u6df3\u6c11", "scr_acptcnt": 55.0, "sub_name": "PHYS107 \u666e\u901a\u7269\u7406(\u4e00)", "scj_scr_mso": "\u5fc5\u4fee", "scr_precnt": 8.0, "year": 105, "semester": 1, "scr_selcode": "1155", "scr_credit": 2.0, "unt_ls": 4603, "scr_dup": "001", "scr_remarks": " ", "cls_name": "\u6c34\u5229\u8207\u8cc7\u4fdd\u4e00\u7532", "sub_id": "48560", "scr_exambf": "\u5426", "cls_id": "CE02111", "scr_examid": "\u5426", "scr_examfn": "\u5426"}, "1052CE0413369930001": {"scr_period": "(\u4e8c)06-08 \u8a9e207 \u6731\u667a\u7fa9", "scr_acptcnt": 81.0, "sub_name": "MCAE301 \u6a5f\u68b0\u8a2d\u8a08(\u4e00)", "scj_scr_mso": "\u5fc5\u4fee", "scr_precnt": 75.0, "year": 105, "semester": 1, "scr_selcode": "1388", "scr_credit": 3.0, "unt_ls": 4009, "scr_dup": "001", "scr_remarks": " ", "cls_name": "\u6a5f\u96fb\u4e09\u4e19", "sub_id": "69930", "scr_exambf": "\u5426", "cls_id": "CE04133", "scr_examid": "\u5426", "scr_examfn": "\u5426"}, "1052CB0511200001001": {"scr_period": "(\u4e8c)08-09 \u8a9e401 \u8cf4\u708e\u537f,\u9ec3\u5b9a\u9060", "scr_acptcnt": 54.0, "sub_name": "UNIV902 \u73ed\u7d1a\u6d3b\u52d5", "scj_scr_mso": "\u5fc5\u4fee", "scr_precnt": 60.0, "year": 105, "semester": 1, "scr_selcode": "0408", "scr_credit": 0.0, "unt_ls": 4104, "scr_dup": "001", "scr_remarks": " ", "cls_name": "\u8ca1\u7a05\u4e00\u4e59", "sub_id": "00001", "scr_exambf": "\u5426", "cls_id": "CB05112", "scr_examid": "\u5426", "scr_examfn": "\u5426"}, "1052CS0612298237001": {"scr_period": "(\u4e8c)06-07 \u4eba405 \u90ed\u932b\u967d", "scr_acptcnt": 55.0, "sub_name": "GBHC112 \u6587\u660e\u8b8a\u9077", "scj_scr_mso": "\u5fc5\u4fee", "scr_precnt": 78.0, "year": 105, "semester": 1, "scr_selcode": "3292", "scr_credit": 2.0, "unt_ls": 4306, "scr_dup": "001", "scr_remarks": " ", "cls_name": "\u5149\u96fb\u4e8c\u4e59", "sub_id": "98237", "scr_exambf": "\u5426", "cls_id": "CS06122", "scr_examid": "\u5426", "scr_examfn": "\u5426"}, "1052CE1131013568001": {"scr_period": "(\u4e94)07-09 \u8cc7\u96fb312 \u5085\u660e\u5b87", "scr_acptcnt": 9.0, "sub_name": "EEEN660 \u5149\u7e96\u901a\u8a0a\u5c08\u8ad6", "scj_scr_mso": "\u9078\u4fee", "scr_precnt": 20.0, "year": 105, "semester": 1, "scr_selcode": "1920", "scr_credit": 3.0, "unt_ls": 4503, "scr_dup": "001", "scr_remarks": null, "cls_name": "\u96fb\u6a5f\u78a9\u4e00", "sub_id": "13568", "scr_exambf": "\u5426", "cls_id": "CE11310", "scr_examid": "\u5426", "scr_examfn": "\u5426"}, "1052CM0232043130001": {"scr_period": "(\u4e00)02     \u7d00413 \u8449\u540d\u5c71", "scr_acptcnt": 15.0, "sub_name": "TTEM691 \u5c08\u984c\u8a0e\u8ad6(\u4e00)", "scj_scr_mso": "\u5fc5\u4fee", "scr_precnt": 20.0, "year": 105, "semester": 1, "scr_selcode": "2835", "scr_credit": 1.0, "unt_ls": 4606, "scr_dup": "001", "scr_remarks": " ", "cls_name": "\u904b\u7ba1\u78a9\u4e8c", "sub_id": "43130", "scr_exambf": "\u5426", "cls_id": "CM02320", "scr_examid": "\u5426", "scr_examfn": "\u5426"}, "1052CE0114171450001": {"scr_period": "(\u4e00)03-04 \u5fe0210 \u856d\u5bb6\u5b5f", "scr_acptcnt": 18.0, "sub_name": "CE465 \u92fc\u7b4b\u6df7\u51dd\u571f\u623f\u5c4b\u8a2d\u8a08", "scj_scr_mso": "\u9078\u4fee", "scr_precnt": 60.0, "year": 105, "semester": 1, "scr_selcode": "1127", "scr_credit": 2.0, "unt_ls": 4602, "scr_dup": "001", "scr_remarks": null, "cls_name": "\u571f\u6728\u56db\u7532", "sub_id": "71450", "scr_exambf": "\u5426", "cls_id": "CE01141", "scr_examid": "\u5426", "scr_examfn": "\u662f"}, "1052CB0512105931001": {"scr_period": "(\u4e09)06-08 \u5546306 \u8a31\u6167\u96ef", "scr_acptcnt": 79.0, "sub_name": "ACCT201 \u4e2d\u7d1a\u6703\u8a08\u5b78(\u4e00)", "scj_scr_mso": "\u5fc5\u4fee", "scr_precnt": 78.0, "year": 105, "semester": 1, "scr_selcode": "0417", "scr_credit": 3.0, "unt_ls": 4104, "scr_dup": "001", "scr_remarks": " ", "cls_name": "\u8ca1\u7a05\u4e8c\u7532", "sub_id": "05931", "scr_exambf": "\u5426", "cls_id": "CB05121", "scr_examid": "\u5426", "scr_examfn": "\u5426"}, "1052CE2311079872001": {"scr_period": "(\u4e94)00     \u672a\u6392\u6559\u5ba4 \u6d2a\u975c\u8339", "scr_acptcnt": 55.0, "sub_name": "GBIL108 \u8cc7\u8a0a\u7d20\u990a\u4f5c\u696d\u4e8c\uff1a\u5371\u6a5f\u8655\u7406\u5206\u6790", "scj_scr_mso": "\u5fc5\u4fee", "scr_precnt": 60.0, "year": 105, "semester": 1, "scr_selcode": "2128", "scr_credit": 0.0, "unt_ls": 4607, "scr_dup": "001", "scr_remarks": " ", "cls_name": "\u90fd\u8cc7\u4e00\u90fd\u5e02\u8a08\u756b\u7d44", "sub_id": "79872", "scr_exambf": "\u5426", "cls_id": "CE23110", "scr_examid": "\u5426", "scr_examfn": "\u5426"}, "1052CH0613226559002": {"scr_period": "(\u56db)06-07 \u8cc7\u96fbB28(\u96fb\u8166\u5be6\u7fd2\u5ba4) \u6797\u7fa8\u5cef", "scr_acptcnt": 19.0, "sub_name": "FLL301 \u82f1\u6587\u4f5c\u6587(\u4e94)", "scj_scr_mso": "\u5fc5\u4fee", "scr_precnt": 15.0, "year": 105, "semester": 1, "scr_selcode": "2336", "scr_credit": 2.0, "unt_ls": 4406, "scr_dup": "002", "scr_remarks": "\u9650\u5916\u6587\u7cfb\u5b78\u751f\u3002", "cls_name": "\u5916\u6587\u4e09\u4e59", "sub_id": "26559", "scr_exambf": "\u5426", "cls_id": "CH06132", "scr_examid": "\u5426", "scr_examfn": "\u5426"}, "1052CE0112244150001": {"scr_period": "(\u56db)01-02 \u5fe0211 \u9673\u6e05\u6a19", "scr_acptcnt": 68.0, "sub_name": "CE281 \u6e2c\u91cf\u5b78", "scj_scr_mso": "\u5fc5\u4fee", "scr_precnt": 70.0, "year": 105, "semester": 1, "scr_selcode": "1096", "scr_credit": 3.0, "unt_ls": 4602, "scr_dup": "001", "scr_remarks": " ", "cls_name": "\u571f\u6728\u4e8c\u4e59", "sub_id": "44150", "scr_exambf": "\u5426", "cls_id": "CE01122", "scr_examid": "\u662f", "scr_examfn": "\u662f"}, "1052CE0513100001001": {"scr_period": "(\u4e00)09     \u5de5303 \u90b1\u9577\u5864", "scr_acptcnt": 51.0, "sub_name": "UNIV902 \u73ed\u7d1a\u6d3b\u52d5", "scj_scr_mso": "\u5fc5\u4fee", "scr_precnt": 60.0, "year": 105, "semester": 1, "scr_selcode": "1480", "scr_credit": 0.0, "unt_ls": 4008, "scr_dup": "001", "scr_remarks": " ", "cls_name": "\u7e96\u8907\u4e09\u7532", "sub_id": "00001", "scr_exambf": "\u5426", "cls_id": "CE05131", "scr_examid": "\u5426", "scr_examfn": "\u5426"}, "1052CB1451157551001": {"scr_period": "(\u4e09)11-13 \u5546202 \u6c5f\u632f\u744b", "scr_acptcnt": 69.0, "sub_name": "ECON101 \u7d93\u6fdf\u5b78(\u4e00)", "scj_scr_mso": "\u5fc5\u4fee", "scr_precnt": 80.0, "year": 105, "semester": 1, "scr_selcode": "0704", "scr_credit": 3.0, "unt_ls": 4110, "scr_dup": "001", "scr_remarks": " ", "cls_name": "\u5546\u5b78\u9032\u4fee\u4e00\u7532", "sub_id": "57551", "scr_exambf": "\u5426", "cls_id": "CB14511", "scr_examid": "\u5426", "scr_examfn": "\u5426"}, "1052CI0083I56500001": {"scr_period": "(\u4e09)06     \u8cc7\u96fb512 (\u56db)01-02 \u8cc7\u96fb512 \u8607\u6587\u5f6c", "scr_acptcnt": 16.0, "sub_name": "AUTO317 \u96fb\u6a5f\u6a5f\u68b0", "scj_scr_mso": "\u9078\u4fee", "scr_precnt": 60.0, "year": 105, "semester": 1, "scr_selcode": "2471", "scr_credit": 3.0, "unt_ls": 4504, "scr_dup": "001", "scr_remarks": null, "cls_name": "\u751f\u91ab\u5de5\u7a0b\u5b78\u7a0b\u81ea\u63a7\u4e09", "sub_id": "56500", "scr_exambf": "\u5426", "cls_id": "CI0083I", "scr_examid": "\u662f", "scr_examfn": "\u662f"}, "1052CB0613014740001": {"scr_period": "(\u4e00)07-09 \u5546305 \u674e\u6842\u79cb", "scr_acptcnt": 86.0, "sub_name": "MGT220 \u884c\u92b7\u7ba1\u7406", "scj_scr_mso": "\u5fc5\u4fee", "scr_precnt": 90.0, "year": 105, "semester": 1, "scr_selcode": "0484", "scr_credit": 3.0, "unt_ls": 4107, "scr_dup": "001", "scr_remarks": " ", "cls_name": "\u5408\u7d93\u4e09", "sub_id": "14740", "scr_exambf": "\u5426", "cls_id": "CB06130", "scr_examid": "\u5426", "scr_examfn": "\u5426"}, "1052CS0232012570001": {"scr_period": "(\u56db)06-08 \u7406303 \u7ae5\u7fd4\u65b0", "scr_acptcnt": 6.0, "sub_name": "EES621 \u751f\u614b\u5de5\u7a0b\u61c9\u7528", "scj_scr_mso": "\u9078\u4fee", "scr_precnt": 20.0, "year": 105, "semester": 1, "scr_selcode": "3095", "scr_credit": 3.0, "unt_ls": 4303, "scr_dup": "001", "scr_remarks": null, "cls_name": "\u74b0\u5883\u78a9\u4e8c", "sub_id": "12570", "scr_exambf": "\u5426", "cls_id": "CS02320", "scr_examid": "\u5426", "scr_examfn": "\u5426"}, "1052CE0413269930001": {"scr_period": "(\u4e09)06     \u5de5305 (\u56db)03-04 \u5de5305 \u6731\u667a\u7fa9", "scr_acptcnt": 76.0, "sub_name": "MCAE301 \u6a5f\u68b0\u8a2d\u8a08(\u4e00)", "scj_scr_mso": "\u5fc5\u4fee", "scr_precnt": 75.0, "year": 105, "semester": 1, "scr_selcode": "1381", "scr_credit": 3.0, "unt_ls": 4009, "scr_dup": "001", "scr_remarks": " ", "cls_name": "\u6a5f\u96fb\u4e09\u4e59", "sub_id": "69930", "scr_exambf": "\u5426", "cls_id": "CE04132", "scr_examid": "\u5426", "scr_examfn": "\u5426"}, "1052CS0613200001001": {"scr_period": "(\u56db)05     \u7406401 \u9673\u656c\u6052", "scr_acptcnt": 50.0, "sub_name": "UNIV902 \u73ed\u7d1a\u6d3b\u52d5", "scj_scr_mso": "\u5fc5\u4fee", "scr_precnt": 60.0, "year": 105, "semester": 1, "scr_selcode": "3300", "scr_credit": 0.0, "unt_ls": 4306, "scr_dup": "001", "scr_remarks": " ", "cls_name": "\u5149\u96fb\u4e09\u4e59", "sub_id": "00001", "scr_exambf": "\u5426", "cls_id": "CS06132", "scr_examid": "\u5426", "scr_examfn": "\u5426"}, "1052CD0153025543001": {"scr_period": "(\u56db)11-12 \u5fe0309 \u66fe\u5065\u6d32", "scr_acptcnt": 51.0, "sub_name": "ILD342 \u5ba4\u5167\u8a2d\u8a08\u98a8\u683c", "scj_scr_mso": "\u9078\u4fee", "scr_precnt": 60.0, "year": 105, "semester": 1, "scr_selcode": "0989", "scr_credit": 2.0, "unt_ls": 5007, "scr_dup": "001", "scr_remarks": null, "cls_name": "\u5ba4\u5167\u8a2d\u8a08\u9032\u4fee\u4e09", "sub_id": "25543", "scr_exambf": "\u5426", "cls_id": "CD01530", "scr_examid": "\u5426", "scr_examfn": "\u5426"}, "1052CE2312000001001": {"scr_period": "(\u4e09)05     \u7d00111 \u5289\u66dc\u83ef", "scr_acptcnt": 63.0, "sub_name": "UNIV902 \u73ed\u7d1a\u6d3b\u52d5", "scj_scr_mso": "\u5fc5\u4fee", "scr_precnt": 60.0, "year": 105, "semester": 1, "scr_selcode": "2130", "scr_credit": 0.0, "unt_ls": 4607, "scr_dup": "001", "scr_remarks": " ", "cls_name": "\u90fd\u8cc7\u4e8c\u90fd\u5e02\u8a08\u756b\u7d44", "sub_id": "00001", "scr_exambf": "\u5426", "cls_id": "CE23120", "scr_examid": "\u5426", "scr_examfn": "\u5426"}, "1052CE0312279874001": {"scr_period": "(\u56db)00     \u672a\u6392\u6559\u5ba4 \u9673\u4ef2\u5049", "scr_acptcnt": 50.0, "sub_name": "GBIL110 \u8cc7\u8a0a\u7d20\u990a\u4f5c\u696d\u56db\uff1a\u5be6\u969b\u53c3\u8a2a\u5831\u544a", "scj_scr_mso": "\u5fc5\u4fee", "scr_precnt": 65.0, "year": 105, "semester": 1, "scr_selcode": "1249", "scr_credit": 0.0, "unt_ls": 5002, "scr_dup": "001", "scr_remarks": null, "cls_name": "\u5efa\u7bc9\u4e8c\u4e59\u5b78\u4f4d\u5b78\u7a0b", "sub_id": "79874", "scr_exambf": "\u5426", "cls_id": "CE03122", "scr_examid": "\u5426", "scr_examfn": "\u5426"}, "1052XF0110926491002": {"scr_period": "(\u56db)06-07 \u4eba507 (\u4e94)00     \u672a\u6392\u6559\u5ba4 \u9673\u4f9d\u73b2", "scr_acptcnt": 30.0, "sub_name": "LC011 \u82f1\u6587(\u4e00)\u521d\u7d1a", "scj_scr_mso": "\u5fc5\u4fee", "scr_precnt": 35.0, "year": 105, "semester": 1, "scr_selcode": "3916", "scr_credit": 3.0, "unt_ls": 8888, "scr_dup": "002", "scr_remarks": "\u521d\u7d1a\u73ed(\u7b2c1\u7d1a)\u3002\u9078\u8ab2\u65b9\u5f0f\u540c\u4e0a\u3002", "cls_name": "\u8cc7\u96fb\u82f1B\u73ed", "sub_id": "26491", "scr_exambf": "\u5426", "cls_id": "XF01109", "scr_examid": "\u662f", "scr_examfn": "\u5426"}, "1052NM0212000001001": {"scr_period": "(\u4e94)05     \u4eba203 \u66fe\u9f0e\u7fd4", "scr_acptcnt": 14.0, "sub_name": "UNIV902 \u73ed\u7d1a\u6d3b\u52d5", "scj_scr_mso": "\u5fc5\u4fee", "scr_precnt": 17.0, "year": 105, "semester": 1, "scr_selcode": "3340", "scr_credit": 0.0, "unt_ls": 4904, "scr_dup": "001", "scr_remarks": " ", "cls_name": "\u5546\u5b78\u5275\u65b0\u4e8c\u5b78\u4f4d\u5b78\u7a0b", "sub_id": "00001", "scr_exambf": "\u5426", "cls_id": "NM02120", "scr_examid": "\u5426", "scr_examfn": "\u5426"}, "1052CE0414160171001": {"scr_period": "(\u4e00)09-10 \u5de5209 (\u4e09)10     \u5de5209 \u5f6d\u4fe1\u8212", "scr_acptcnt": 35.0, "sub_name": "MCAE489 \u5851\u81a0\u5c04\u51fa\u6a21\u6d41\u5206\u6790\u5be6\u52d9", "scj_scr_mso": "\u9078\u4fee", "scr_precnt": 40.0, "year": 105, "semester": 1, "scr_selcode": "1405", "scr_credit": 3.0, "unt_ls": 4009, "scr_dup": "001", "scr_remarks": null, "cls_name": "\u6a5f\u96fb\u56db\u7532", "sub_id": "60171", "scr_exambf": "\u5426", "cls_id": "CE04141", "scr_examid": "\u5426", "scr_examfn": "\u5426"}, "1052PC4410001150001": {"scr_period": "(\u4e94)08-10 \u7406407 \u674e\u66f8\u5b89,\u8607\u5fb7\u52dd", "scr_acptcnt": 80.0, "sub_name": "EES271 \u5de5\u696d\u885b\u751f", "scj_scr_mso": "\u5fc5\u4fee", "scr_precnt": 80.0, "year": 105, "semester": 1, "scr_selcode": "3443", "scr_credit": 3.0, "unt_ls": 8888, "scr_dup": "001", "scr_remarks": null, "cls_name": "\u52de\u5de5\u5b89\u5168\u885b\u751f\u5b78\u7a0b", "sub_id": "01150", "scr_exambf": "\u5426", "cls_id": "PC44100", "scr_examid": "\u662f", "scr_examfn": "\u662f"}, "1052CS0614243090001": {"scr_period": "(\u4e94)14     \u7406404 \u674e\u82f1\u5fb7,\u8cf4\u4fca\u5cf0", "scr_acptcnt": 20.0, "sub_name": "OPT490 \u5c08\u984c\u7814\u7a76(\u4e8c)", "scj_scr_mso": "\u9078\u4fee", "scr_precnt": 60.0, "year": 105, "semester": 1, "scr_selcode": "3318", "scr_credit": 1.0, "unt_ls": 4306, "scr_dup": "001", "scr_remarks": "\u672c\u8ab2\u7a0b\u4e26\u4e0d\u63a5\u53d7\u7cfb\u5916\u540c\u5b78\u4fee\u7fd2\u3002", "cls_name": "\u5149\u96fb\u56db\u4e59", "sub_id": "43090", "scr_exambf": "\u5426", "cls_id": "CS06142", "scr_examid": "\u5426", "scr_examfn": "\u5426"}, "1052CB1641076955001": {"scr_period": "(\u516d)02-04 \u5546702 \u6797\u9e97\u82ac", "scr_acptcnt": 2.0, "sub_name": "HECO709 \u91ab\u7642\u7d93\u6fdf\u5c08\u984c", "scj_scr_mso": "\u5fc5\u4fee", "scr_precnt": 10.0, "year": 105, "semester": 1, "scr_selcode": "0808", "scr_credit": 3.0, "unt_ls": 4109, "scr_dup": "001", "scr_remarks": " ", "cls_name": "\u5546\u5b78\u535a\u4e00\u5b78\u4f4d\u5b78\u7a0b", "sub_id": "76955", "scr_exambf": "\u5426", "cls_id": "CB16410", "scr_examid": "\u5426", "scr_examfn": "\u5426"}, "1052CB15312B3035001": {"scr_period": "(\u4e09)09-10 \u5546707 \u90b5\u4f0a\u82ac", "scr_acptcnt": 25.0, "sub_name": "ELAW706 \u5211\u6cd5\u7e3d\u5247", "scj_scr_mso": "\u5fc5\u4fee", "scr_precnt": 30.0, "year": 105, "semester": 1, "scr_selcode": "0781", "scr_credit": 2.0, "unt_ls": 4111, "scr_dup": "001", "scr_remarks": " ", "cls_name": "\u8ca1\u6cd5\u78a9\u4e00\u6cd5\u5f8b\u5c08\u696d\u7d44", "sub_id": "B3035", "scr_exambf": "\u5426", "cls_id": "CB15312", "scr_examid": "\u5426", "scr_examfn": "\u5426"}}